<?xml version='1.0' encoding='ISO-8859-1'?>
<!--
# Copyright (c) 1986-2018 Pixar. All rights reserved.
#
# The information in this file (the "Software") is provided for the exclusive
# use of the software licensees of Pixar ("Licensees").  Licensees have the
# right to incorporate the Software into other products for use by other
# authorized software licensees of Pixar, without fee. Except as expressly
# permitted herein, the Software may not be disclosed to third parties, copied
# or duplicated in any form, in whole or in part, without the prior written
# permission of Pixar.
#
# The copyright notices in the Software and this entire statement, including the
# above license grant, this restriction and the following disclaimer, must be
# included in all copies of the Software, in whole or in part, and all permitted
# derivative works of the Software, unless such copies or derivative works are
# solely in the form of machine-executable object code generated by a source
# language processor.
#
# PIXAR DISCLAIMS ALL WARRANTIES WITH REGARD TO THIS SOFTWARE, INCLUDING ALL
# IMPLIED WARRANTIES OF MERCHANTABILITY AND FITNESS. IN NO EVENT SHALL PIXAR BE
# LIABLE FOR ANY SPECIAL, INDIRECT OR CONSEQUENTIAL DAMAGES OR ANY DAMAGES
# WHATSOEVER RESULTING FROM LOSS OF USE, DATA OR PROFITS, WHETHER IN AN ACTION
# OF CONTRACT, NEGLIGENCE OR OTHER TORTIOUS ACTION, ARISING OUT OF OR IN
# CONNECTION WITH THE USE OR PERFORMANCE OF THIS SOFTWARE.  IN NO CASE WILL
# PIXAR'S TOTAL LIABILITY FOR ALL DAMAGES ARISING OUT OF OR IN CONNECTION WITH
# THE USE OR PERFORMANCE OF THIS SOFTWARE EXCEED $50.
#
# Pixar
# 1200 Park Ave
# Emeryville CA 94608
-->

<?xml-stylesheet type="text/xsl" href="#stylesheet"?>
<!DOCTYPE doc [ 
<!ATTLIST xsl:stylesheet
  id    ID    #REQUIRED> 
]>
<doc>
<xsl:stylesheet version="1.0"
                id="stylesheet"
                xmlns:rm="http://renderman.pixar.com"
                xmlns:xsl="http://www.w3.org/1999/XSL/Transform">
<xsl:output method="html" media-type="text/html" 
            version="4.0" encoding="iso-8859-1" indent="yes"/>
<xsl:template match="xsl:stylesheet" />

<!-- The root of the XML tree is a statsDoc.  Just output some base html -->
<xsl:template match="rm:statsDoc">
<html style="height: 100%; width: 100%;">
  <head>
    <title>Rendering stats</title>
    <!-- Copy xml into the DOM.-->
    <xsl:copy>
        <xsl:attribute name="hidden"/>
        <xsl:attribute name="id">xml_data</xsl:attribute>
        <xsl:apply-templates select="@*|node()"/>
    </xsl:copy>
    <!-- Include inline style sheet.-->
    <xsl:call-template name="InlineScript"/>
  </head>
  <body>
      <div id="main"> 
      </div>
  </body>
</html>
</xsl:template>

<xsl:template match="@*|node()">
  <xsl:copy>
    <xsl:apply-templates select="@*|node()"/>
  </xsl:copy>
</xsl:template>


<xsl:template name="InlineScript">
  <!-- Script to load the rmanStats.js file which does the actual work -->
  <script> 
    /** load a javascript from a url */
    function loadScript(url, onLoad, onError)
    {
        var head = document.getElementsByTagName('head')[0];
        var script = document.createElement('script');
        script.type = 'text/javascript';
        script.src = url;

        // Then bind the event to the callback function.
        // There are several events for cross browser compatibility.
        script.onreadystatechange = onLoad;
        script.onload = onLoad;
        script.onerror = onError;

        //Fire the loading
        head.appendChild(script);
    }
    
    var onLoadBootStrap = function(jsLoaded) {
      console.log("rmanStats_2.0.js loaded from " + jsLoaded.name + ": " 
                  + jsLoaded.url);
    };
    
    /* For the case that the script isn't loaded from a url,
      go to the next in line.
    */
    var onError = function(jsLocations) {
      console.log("rmanStats_2.0.js specified in " + jsLocations[0].name + 
                  " , " + jsLocations[0].url + " not found.");

      if(jsLocations.length > 1) {
        var newLocations = jsLocations.slice(1, jsLocations.length);
        loadScript(newLocations[0].url, 
                  function() { onLoadBootStrap(newLocations[0]);}, 
                  function() { onError(newLocations[0]);});
      }
      else {
        alert("No javascript found for rendering stats page!");
      }
    };
    
    //a list of locations where we can find the js for rendering xml
    jsLocations = [];

    //stats compatability version
    statsVersion =<xsl:value-of select='statsview/version'></xsl:value-of>;
    
    //check if browser has localstorage and check for user setting
    if(typeof window.localStorage != 'undefined') {
      if (localStorage.rmanStatsScript) {
        jsLocations.push({name: 'user setting', 
                          url: localStorage.rmanStatsScript});
      }
    }

    //first check in the xml rmantree setting
    jsFile = "js/rmanStats_2.0.js";
    rmantreeHtml = "<xsl:value-of select='statsview/rmanHtmlDir'>
                    </xsl:value-of>";
    jsLocations.push({name: 'rmantree in xml', url:rmantreeHtml + jsFile});

    //check if networkHtml setting is set
    networkHtml = "<xsl:value-of select='statsview/networkHtmlDir'>
                  </xsl:value-of>";
    if(networkHtml != '') {
      jsLocations.push({name: 'network setting', url: networkHtml + '/' 
                        + statsVersion + '/' + jsFile});
    }
    
    //finally use the one found on renderman.pixar.com
    rmanURL = "https://renderman.pixar.com/statsview/";
    jsLocations.push({name: 'www', url: rmanURL + statsVersion + "/" + jsFile});

    //try to load the first js file specified, will chain to next if error
    loadScript(jsLocations[0].url, 
                function() { onLoadBootStrap(jsLocations[0]);}, 
                function() { onError(jsLocations) });
  </script>
</xsl:template>

</xsl:stylesheet>


<rm:statsDoc xmlns:rm="http://renderman.pixar.com" xmlns:xsi="http://www.w3.org/2001/XMLSchema-instance" xsi:schemaLocation="http://renderman.pixar.com http://renderman.pixar.com/schema/rmStats_1.1.xsd" rmanHtmlDir="C:/Program Files/Pixar/RenderManProServer-22.1/etc/statsview/">
    <statsview>
	<version>2</version>
	<rmanHtmlDir>C:/Program Files/Pixar/RenderManProServer-22.1/etc/statsview/</rmanHtmlDir>
    </statsview>
    <stats name="frame3" description="Rendering statistics" kind="frame">
	<stats name="time" description="Timing summary" kind="section">
	    <string name="timersNote" description="Note:">Sum of component times may exceed total in multi-threaded renders.</string>
	    <stats name="timers" kind="timers">
		<timer name="totaltime" description="Total time">
		    <elapsed>13.322598</elapsed>
		    <user>37.906250</user>
		    <system>5.093750</system>
		</timer>
		<timer name="allProceduralTimers" description="All procedurals">
		    <elapsed>0.000000</elapsed>
		    <user>0.000000</user>
		    <system>0.000000</system>
		</timer>
		<timer name="temporalVolumeBufferTimer" description="Time to create motion data for temporal volume">
		    <elapsed>0.000000</elapsed>
		</timer>
		<timer name="implicitPluginTimers" description="All Implicit and Volume plugins">
		    <elapsed>0.000000</elapsed>
		</timer>
		<timer name="rayTraceTime" description="Tracing rays">
		    <elapsed>8.525487</elapsed>
		</timer>
		<timer name="lightdbtime" description="Light Database Build Time">
		    <elapsed>0.000000</elapsed>
		</timer>
		<timer name="texture3DBrickmapTime" description="Total brickmap texture3d()">
		    <elapsed>0.000000</elapsed>
		</timer>
		<timer name="texture3DPointcloudTime" description="Total pointcloud texture3d()">
		    <elapsed>0.000000</elapsed>
		</timer>
		<timer name="textureTime" description="Texture">
		    <elapsed>0.000000</elapsed>
		</timer>
		<timer name="displayTime" description="Display driver time">
		    <elapsed>0</elapsed>
		</timer>
		<timer name="pluginTimers" description="Plugin timers">
		    <elapsed>1.030965</elapsed>
		</timer>
		<stats name="plugins" description="Plugin statistics" kind="timers">
		    <timer name="PxrSurface[Chair_Leg_Shader_Pxr]::BeginBxdf" description="PxrSurface[Chair_Leg_Shader_Pxr]::BeginBxdf">
			<elapsed>0.407923</elapsed>
		    </timer>
		    <timer name="PxrSurface[Chair_Plastic_Shader_Pxr]::BeginBxdf" description="PxrSurface[Chair_Plastic_Shader_Pxr]::BeginBxdf">
			<elapsed>0.623041</elapsed>
		    </timer>
		</stats>
		<timer name="ribInitTimer" description="Initial rib parsing and setup">
		    <elapsed>0.000000</elapsed>
		    <user>0.000000</user>
		    <system>0.000000</system>
		</timer>
	    </stats>
	</stats>
	<stats name="memory" description="Memory usage summary" kind="section">
	    <stats name="systemMem" description="System memory">
		<memory name="heapMemory" description="Total heap memory">
		    <peak>996634182</peak>
		    <current>996634182</current>
		</memory>
		<memory name="peakResidentSize" description="Peak process size">
		    <peak>1321459712</peak>
		    <current>1321459712</current>
		</memory>
		<int name="pageFaults">2422993</int>
		<int name="peakPageUsage">1859915776</int>
		<int name="peakPagePoolUsage">2855496</int>
	    </stats>
	    <stats name="subsystems" kind="memstats">
		<memory name="geometryMem" description="Geometry Memory">
		    <peak>8112899</peak>
		    <current>585360</current>
		</memory>
		<memory name="implicitPluginMemory" description="Implicit and Volume plugin Memory">
		    <peak>0</peak>
		    <current>0</current>
		</memory>
		<memory name="gridMemByType" description="Grid memory">
		    <peak>2248824</peak>
		    <current>591336</current>
		</memory>
		<memory name="rayAccelMem" description="Ray Accelerator Subsystem">
		    <peak>44814700</peak>
		    <current>44814700</current>
		</memory>
		<memory name="gutCacheMem" description="Tessellation (GUT) cache">
		    <peak>35848200</peak>
		    <current>4194304</current>
		</memory>
		<memory name="radioCacheMem" description="Opacity cache">
		    <peak>185040904</peak>
		    <current>185040904</current>
		</memory>
		<memory name="vaMem" description="Volume aggregate memory">
		    <peak>0</peak>
		    <current>0</current>
		</memory>
		<memory name="pooledmemory" description="Pooled Memory">
		    <peak>58720592</peak>
		    <current>58720592</current>
		</memory>
		<memory name="lightdbmemory" description="Light Database Memory">
		    <peak>0</peak>
		    <current>0</current>
		</memory>
		<memory name="lighthierarchymem" description="Light Hierarchy Memory">
		    <peak>0</peak>
		    <current>0</current>
		</memory>
		<int name="lightdbsize" description="Light Database Patch Count">0</int>
		<memory name="textureMemory" description="Texture cache">
		    <peak>100698376</peak>
		    <current>100698376</current>
		</memory>
		<memory name="ptexMemory" description="PTexture cache">
		    <peak>1376</peak>
		    <current>1376</current>
		</memory>
		<memory name="brickMemSum" description="Brickmap memory">
		    <peak>13415528</peak>
		    <current>524288</current>
		</memory>
		<memory name="pointMemSum" description="Pointcloud memory">
		    <peak>4105456</peak>
		    <current>4105456</current>
		</memory>
		<memory name="SymbolMem" description="Ri Symbol Table memory">
		    <peak>42328</peak>
		    <current>7256</current>
		</memory>
		<memory name="displayMem" description="Display driver memory">
		    <peak>0</peak>
		    <current>0</current>
		</memory>
		<memory name="pluginMemory" description="Plugin storage">
		    <peak>9298835</peak>
		    <current>0</current>
		</memory>
		<stats name="plugins" description="Plugin statistics" kind="memstats">
		    <memory name="pathtracerBufferMemory" description="Pathtracer Buffers">
			<peak>9298835</peak>
			<current>0</current>
		    </memory>
		    <memory name="pathtracerAOVMemory" description="Pathtracer AOVs">
			<peak>0</peak>
			<current>0</current>
		    </memory>
		</stats>
		<memory name="InlineArchiveMem" description="Inline archive memory">
		    <peak>0</peak>
		    <current>0</current>
		</memory>
		<memory name="usrAttrMem" description="User attribute memory">
		    <peak>476</peak>
		    <current>476</current>
		</memory>
		<memory name="coordSysMem" description="Named coordinate system memory">
		    <peak>392</peak>
		    <current>392</current>
		</memory>
	    </stats>
	    <memory name="subsystemMem" description="Subsystem memory total">
		<peak>489983348</peak>
		<current>414174505</current>
	    </memory>
	</stats>
	<stats name="geometry" description="Geometry stats" kind="section">
	    <int name="proceduralsMade" description="Procedurals created">0</int>
	    <int name="proceduralsExpanded" description="Procedurals expanded">0</int>
	    <int name="polyRibVertexCount" description="poly rib vertex count">0</int>
	    <int name="polyRibPolyCount" description="poly rib polygon count">0</int>
	    <int name="subdRibVertexCount" description="subd cage vertex count">30480</int>
	    <int name="subdRibPolyCount" description="subd cage polygon count">7702</int>
	    <int name="curveRibVertexCount" description="curve rib vertex count">25</int>
	    <int name="curveRibStrandCount" description="curve rib strand count">1</int>
	    <int name="polyTriCountFine" description="raytraced poly triangle count (fine)">0</int>
	    <int name="polyTriCountMedium" description="raytraced poly triangle count (medium)">0</int>
	    <int name="polyTriCountCoarse" description="raytraced poly triangle count (coarse)">0</int>
	    <int name="polyTriCountOverall" description="raytraced poly triangle count (overall)">0</int>
	    <int name="subdTriCountFine" description="raytraced subd triangle count (fine)">40470</int>
	    <int name="subdTriCountMedium" description="raytraced subd triangle count (medium)">3094</int>
	    <int name="subdTriCountCoarse" description="raytraced subd triangle count (coarse)">0</int>
	    <int name="subdTriCountOverall" description="raytraced subd triangle count (overall)">40740</int>
	    <memory name="gsmMem" description="GSM memory">
		<peak>13920</peak>
		<current>13920</current>
	    </memory>
	    <memory name="matrixMem" description="Matrix memory">
		<peak>13176</peak>
		<current>5784</current>
	    </memory>
	    <range name="gprimCount" description="GPrim count">
		<current>3</current>
		<total>11936</total>
		<min>0</min>
		<max>1263</max>
		<average>1</average>
		<count>11936</count>
	    </range>
	    <memory name="gprimMem" description="GPrim memory">
		<peak>1135856</peak>
		<current>344272</current>
	    </memory>
	    <memory name="gopStaticMem" description="Static GOP memory">
		<peak>4392</peak>
		<current>-5352</current>
	    </memory>
	    <memory name="gopDynamicMem" description="Dynamic GOP memory">
		<peak>92208</peak>
		<current>5616</current>
	    </memory>
	    <memory name="stitchMem" description="Crack reduction memory">
		<peak>0</peak>
		<current>0</current>
	    </memory>
	    <range name="vvCount" description="Vertex vector count">
		<current>0</current>
		<total>2791</total>
		<min>0</min>
		<max>912</max>
		<average>1</average>
		<count>2791</count>
	    </range>
	    <memory name="vvMem" description="Vertex vector memory">
		<peak>5666827</peak>
		<current>221120</current>
	    </memory>
	    <memory name="vvOverheadMem" description="Vertex vector overhead memory">
		<peak>206808</peak>
		<current>0</current>
	    </memory>
	    <stats name="implicitSurfacePlugins" description="Stats for each Implicit and Volume plugin" kind="implicitplugins">
	    </stats>
	    <memory name="catmarkMem" description="Catmull-Clark subdivision memory">
		<peak>979712</peak>
		<current>0</current>
	    </memory>
	    <memory name="loopMem" description="Loop subdivision memory">
		<peak>0</peak>
		<current>0</current>
	    </memory>
	    <memory name="trimCurveMem" description="Trim curve memory">
		<peak>0</peak>
		<current>0</current>
	    </memory>
	    <memory name="trimDataMem" description="Trim data memory">
		<peak>0</peak>
		<current>0</current>
	    </memory>
	    <memory name="temporalVolumeBufferMem" description="temporal volume buffer memory">
		<peak>0</peak>
		<current>0</current>
	    </memory>
	    <stats name="procedurals" description="Per-procedural statistics" kind="geometryprocedurals">
	    </stats>
	</stats>
	<stats name="grids" description="Grid stats" kind="section">
	    <stats name="gridsCount" description="Grid count">
		<range name="rectangular" description="">
		    <current>114</current>
		    <total>9712</total>
		    <min>0</min>
		    <max>1364</max>
		    <average>1</average>
		    <count>9712</count>
		</range>
	    </stats>
	    <stats name="gridSizeByType" description="Grid size">
		<range name="rectangular" description="">
		    <current>116</current>
		    <total>122548</total>
		    <min>0</min>
		    <max>1257</max>
		    <average>12.6182</average>
		    <count>9712</count>
		</range>
	    </stats>
	    <stats name="gridMemByType" description="Grid memory">
		<memory name="rectangular" description="">
		    <peak>2248824</peak>
		    <current>591336</current>
		</memory>
	    </stats>
	    <stats name="subdivAPIHugeGridMem" description="Subdivision Surface API">
	    </stats>
	</stats>
	<stats name="rayAccel" description="Ray accelerator stats" kind="section">
	    <int name="initialRTPrims" description="Initial gprims">15</int>
	    <int name="finalRTPrims" description="All gprims after splits">982</int>
	    <int name="raysShot" description="Total rays">22053691</int>
	    <int name="bboxTests" description="BBox tests">0</int>
	    <int name="gprimBBoxTests" description="Gprim BBox tests">24604372</int>
	    <stats name="primTestsByType" description="Primitive tests by type">
		<int name="catmarkface" description="">662557</int>
		<int name="bsplinepatch" description="">1672041</int>
		<int name="hedronsplit" description="">4914242</int>
		<int name="analyticlight" description="">33090</int>
	    </stats>
	    <stats name="primHitsByType" description="Primitive hits by type">
		<int name="catmarkface" description="">179534</int>
		<int name="bsplinepatch" description="">553500</int>
		<int name="hedronsplit" description="">1538625</int>
	    </stats>
	    <int name="transmissionRayContinuations" description="Transmission ray continuations">0</int>
	    <stats name="raysByType" description="Rays by type">
		<int name="camera" description="">16816195</int>
		<int name="transmission" description="">925910</int>
		<int name="directlight" description="">1641601</int>
		<int name="indirect" description="">1744075</int>
	    </stats>
	    <int name="transmissionBeforeCull" description="Transmission Rays before Culling">925910</int>
	    <timer name="cameraTime" description="Time tracing camera rays">
		<elapsed>4.968121</elapsed>
	    </timer>
	    <timer name="photonTime" description="Time tracing photon rays">
		<elapsed>0.000000</elapsed>
	    </timer>
	    <timer name="transmissionTime" description="Time tracing transmission rays">
		<elapsed>1.104649</elapsed>
	    </timer>
	    <timer name="indirectTime" description="Time tracing indirect rays">
		<elapsed>2.205857</elapsed>
	    </timer>
	    <timer name="directlightTime" description="Time tracing direct lighting rays">
		<elapsed>0.246860</elapsed>
	    </timer>
	    <timer name="splitTime" description="Time splitting prims">
		<elapsed>0.405277</elapsed>
	    </timer>
	    <timer name="buildTime" description="Time building hierarchy">
		<elapsed>0.007273</elapsed>
	    </timer>
	    <timer name="subAccelBuildTime" description="Time building sub-acceleration data structures">
		<elapsed>0.048755</elapsed>
	    </timer>
	    <timer name="subAccelDispTime" description="Time displacing sub-acceleration data structures">
		<elapsed>0.000000</elapsed>
	    </timer>
	    <histogram name="rayDepthHistogram" description="Ray depth histogram">
		<bin label="0">18560270</bin>
		<bin label="1">2567511</bin>
		<bin label="2">0</bin>
		<bin label="3">0</bin>
		<bin label="4">0</bin>
		<bin label="5">0</bin>
		<bin label="6">0</bin>
		<bin label="7">0</bin>
		<bin label="8">0</bin>
		<bin label="9">0</bin>
		<bin label="more">0</bin>
	    </histogram>
	    <memory name="acceleratorMem" description="Ray accelerator memory">
		<peak>44814700</peak>
		<current>44814700</current>
	    </memory>
	    <int name="primTests" description="Primitive tests">7281930</int>
	    <int name="primHits" description="Primitive hits">2271659</int>
	</stats>
	<stats name="rayGprim" description="Ray gprim stats" kind="section">
	    <int name="triTests" description="Triangle hit tests">1563298</int>
	    <int name="triHits" description="Triangle hits">745292</int>
	    <int name="flatQuadTests" description="Flat BLP hit tests">0</int>
	    <int name="flatQuadHits" description="Flat BLP hits">0</int>
	    <int name="curvedQuadTests" description="Curved BLP hit tests">0</int>
	    <int name="curvedQuadHits" description="Curved BLP hits">0</int>
	    <int name="oneSidedRejects" description="Rejected hits due to Sides 1">0</int>
	    <int name="nurbsHitTotal" description="NURB hits">0</int>
	    <int name="nurbsHitTrimmed" description="NURB hits that were trimmed">0</int>
	    <int name="catmarkGridCacheHits" description="Catmark grid cache hits">702105</int>
	    <int name="catmarkGridCacheMisses" description="Catmark grid cache misses">0</int>
	    <int name="gutDisplacementShaded" description="Displacement shaded points during tessellation">0</int>
	    <int name="gutRadiosityShaded" description="Surface shaded points during opacity caching">0</int>
	    <timer name="gutFirstTimeToFill" description="Tessellation (GUT) cache creating entries (compulsory misses)">
		<elapsed>0.008755</elapsed>
	    </timer>
	    <timer name="gutOtherTimeToFill" description="Tessellation (GUT) cache creating entries (capacity misses)">
		<elapsed>0.007988</elapsed>
	    </timer>
	    <stats name="gutCacheLookups" description="Tessellation (GUT) cache lookups">
		<int name="coarse" description="">29089</int>
		<int name="medium" description="">36576</int>
		<int name="fine" description="">2268933</int>
	    </stats>
	    <stats name="gutCacheHits" description="Tessellation (GUT) cache hits">
		<int name="coarse" description="">29089</int>
		<int name="medium" description="">36400</int>
		<int name="fine" description="">2268760</int>
	    </stats>
	    <stats name="gutCacheMisses" description="Tessellation (GUT) cache misses">
		<int name="coarse" description="">0</int>
		<int name="medium" description="">176</int>
		<int name="fine" description="">173</int>
	    </stats>
	    <stats name="gutCacheL1Misses" description="Tessellation (GUT) cache L1 misses">
		<int name="coarse" description="">0</int>
		<int name="medium" description="">1197</int>
		<int name="fine" description="">1208</int>
	    </stats>
	    <memory name="gutCacheMem" description="Tessellation (GUT) cache">
		<peak>35848200</peak>
		<current>4194304</current>
	    </memory>
	    <timer name="radioTimeToFill" description="Opacity cache creating entries">
		<elapsed>0.000000</elapsed>
	    </timer>
	    <stats name="radioCacheLookups" description="Opacity cache lookups">
		<int name="coarse" description="">0</int>
		<int name="medium" description="">0</int>
		<int name="fine" description="">0</int>
		<int name="constant" description="">0</int>
	    </stats>
	    <stats name="radioCacheHits" description="Opacity cache hits">
		<int name="coarse" description="">0</int>
		<int name="medium" description="">0</int>
		<int name="fine" description="">0</int>
		<int name="constant" description="">0</int>
	    </stats>
	    <stats name="radioCacheMisses" description="Opacity cache misses">
		<int name="coarse" description="">0</int>
		<int name="medium" description="">0</int>
		<int name="fine" description="">0</int>
		<int name="constant" description="">0</int>
	    </stats>
	    <memory name="radioCacheMem" description="Opacity cache">
		<peak>185040904</peak>
		<current>185040904</current>
	    </memory>
	    <stats name="radioCacheEvictions" description="Opacity cache evictions">
		<int name="coarse" description="">0</int>
		<int name="medium" description="">0</int>
		<int name="fine" description="">0</int>
		<int name="constant" description="">0</int>
	    </stats>
	    <stats name="radioReuseRates" description="Opacity reuse rates">
		<float name="coarse" description="">0</float>
		<float name="medium" description="">0</float>
		<float name="fine" description="">0</float>
		<float name="constant" description="">0</float>
	    </stats>
	    <memory name="vaMem" description="Volume aggregate memory">
		<peak>0</peak>
		<current>0</current>
	    </memory>
	    <int name="vaNumVolumes" description="Volumes in aggregate">0</int>
	    <int name="vaNumRays" description="Volume aggregate rays">0</int>
	    <int name="vaNumSegments" description="Volume aggregate segments">0</int>
	    <int name="vaNumSteps" description="Volume aggregate steps">0</int>
	    <int name="vaNumRegions" description="Volume aggregate regions">0</int>
	    <int name="vaNumEntries" description="Volume aggregate entries">0</int>
	    <int name="vaNumComputes" description="Volume aggregate computations">0</int>
	</stats>
	<stats name="bounds" description="Unusual displacements" kind="section">
	    <stats name="dispbounds" description="Displacement bounds">
	    </stats>
	</stats>
	<stats name="texture" description="texture" kind="section">
	    <stats name="textureTileCache" description="Texture cache" kind="section">
		<memory name="size" description="Cache size">
		    <peak>100698376</peak>
		    <current>100698376</current>
		</memory>
		<int name="maxTiles" description="Max tiles">813440</int>
		<int name="tilesUsed" description="Num tiles used">0</int>
		<int name="tilesRead" description="Num tiles read">0</int>
		<int name="lookups" description="Lookups">0</int>
		<int name="hits" description="Hits">0</int>
		<int name="misses" description="Misses">0</int>
		<int name="bytesRead" description="Bytes read">0</int>
		<timer name="readTime" description="Read">
		    <elapsed>0.000000</elapsed>
		</timer>
		<timer name="decompressTime" description="Decompress">
		    <elapsed>0.000000</elapsed>
		</timer>
	    </stats>
	    <stats name="textureFiltering" description="Texture filtering" kind="section">
		<timer name="filterTime" description="Filtering time">
		    <elapsed>0.000000</elapsed>
		</timer>
		<int name="requests" description="Requests">0</int>
		<int name="samples" description="Samples">0</int>
		<histogram name="samplesHist" description="# samples per request">
		    <bin label="2">0</bin>
		    <bin label="4">0</bin>
		    <bin label="8">0</bin>
		    <bin label="16">0</bin>
		    <bin label="32">0</bin>
		    <bin label="64">0</bin>
		    <bin label="128">0</bin>
		    <bin label="256">0</bin>
		    <bin label="512">0</bin>
		    <bin label="1024">0</bin>
		    <bin label="2048">0</bin>
		    <bin label="4096">0</bin>
		    <bin label="more">0</bin>
		</histogram>
		<histogram name="filterWidthHist" description="Max filter width">
		    <bin label="1">0</bin>
		    <bin label="2">0</bin>
		    <bin label="3">0</bin>
		    <bin label="4">0</bin>
		    <bin label="5">0</bin>
		    <bin label="6">0</bin>
		    <bin label="7">0</bin>
		    <bin label="8">0</bin>
		    <bin label="9">0</bin>
		    <bin label="10">0</bin>
		    <bin label="11">0</bin>
		    <bin label="12">0</bin>
		    <bin label="more">0</bin>
		</histogram>
	    </stats>
	    <stats name="environmentFiltering" description="Environment filtering" kind="section">
		<timer name="filterTime" description="Filtering time">
		    <elapsed>0.000000</elapsed>
		</timer>
		<int name="requests" description="Requests">0</int>
		<int name="samples" description="Samples">0</int>
		<histogram name="samplesHist" description="# samples per request">
		    <bin label="2">0</bin>
		    <bin label="4">0</bin>
		    <bin label="8">0</bin>
		    <bin label="16">0</bin>
		    <bin label="32">0</bin>
		    <bin label="64">0</bin>
		    <bin label="128">0</bin>
		    <bin label="256">0</bin>
		    <bin label="512">0</bin>
		    <bin label="1024">0</bin>
		    <bin label="2048">0</bin>
		    <bin label="4096">0</bin>
		    <bin label="more">0</bin>
		</histogram>
		<histogram name="filterWidthHist" description="Max filter width">
		    <bin label="1">0</bin>
		    <bin label="2">0</bin>
		    <bin label="3">0</bin>
		    <bin label="4">0</bin>
		    <bin label="5">0</bin>
		    <bin label="6">0</bin>
		    <bin label="7">0</bin>
		    <bin label="8">0</bin>
		    <bin label="9">0</bin>
		    <bin label="10">0</bin>
		    <bin label="11">0</bin>
		    <bin label="12">0</bin>
		    <bin label="more">0</bin>
		</histogram>
	    </stats>
	    <stats name="ptextureCache" description="PTex cache" kind="section">
		<memory name="ptxMem" description="Total Memory">
		    <peak>1376</peak>
		    <current>1376</current>
		</memory>
		<memory name="ptxFileMem" description="File Memory">
		    <peak>0</peak>
		    <current>0</current>
		</memory>
		<memory name="ptxDataMem" description="Data Memory">
		    <peak>0</peak>
		    <current>0</current>
		</memory>
		<memory name="ptxOverheadMem" description="Overhead Memory">
		    <peak>1376</peak>
		    <current>1376</current>
		</memory>
		<int name="ptxFAccessed" description="File Accessed">0</int>
		<int name="ptxFMisses" description="File Misses">0</int>
		<int name="ptxFilesOpen" description="Current Files Open">0</int>
		<int name="ptxPeakFiles" description="Peak Files Open">0</int>
		<int name="ptxBlockReads" description="Blocks Read">0</int>
	    </stats>
	    <stats name="PTex Filtering" description="PTex Filtering" kind="section">
		<timer name="ptexFilter" description="Ptex Filtering Time">
		    <elapsed>0.000000</elapsed>
		</timer>
		<int name="ptexRequests" description="Ptex Requests">0</int>
		<timer name="ptexEnvFilter" description="Ptex Env Filtering Time">
		    <elapsed>0.000000</elapsed>
		</timer>
		<int name="ptexEnvRequests" description="Ptex Env Requests">0</int>
	    </stats>
	    <stats name="textureFiles" description="Texture files" kind="section">
	    </stats>
	</stats>
	<stats name="brickmaps" description="Brick map and brick cache stats" kind="section">
	    <int name="nBrickMapLookups" description="Brick map lookups (texture3d() calls)">0</int>
	    <int name="nBrickMapsAccessed" description="Brick maps accessed">0</int>
	    <int name="nReadHeaderBytes" description="Brick map header bytes read">0</int>
	    <int name="nReadBrickBytes" description="Brick bytes read">0</int>
	    <memory name="brickLocationTableMem" description="Brick location table memory">
		<peak>0</peak>
		<current>0</current>
	    </memory>
	    <memory name="brickmapOctreeMem" description="Brick map octree memory">
		<peak>0</peak>
		<current>0</current>
	    </memory>
	    <memory name="brickmapGprimMem" description="Brick map gprim memory (RT only)">
		<peak>0</peak>
		<current>0</current>
	    </memory>
	    <int name="nBrickCacheLookups" description="Brick cache lookups">0</int>
	    <int name="nBrickCacheHits" description="Brick cache hits">0</int>
	    <int name="nBrickCacheCompMisses" description="Compulsory cache misses">0</int>
	    <int name="nBrickCacheCapaMisses" description="Capacity cache misses">0</int>
	    <histogram name="brickMapLevelHistogram" description="Cache lookup levels">
		<bin label="0">0</bin>
		<bin label="1">0</bin>
		<bin label="2">0</bin>
		<bin label="3">0</bin>
		<bin label="4">0</bin>
		<bin label="5">0</bin>
		<bin label="6">0</bin>
		<bin label="7">0</bin>
		<bin label="8">0</bin>
		<bin label="9">0</bin>
		<bin label="more">0</bin>
	    </histogram>
	    <int name="nBrickCacheElems" description="Brick slots in brick caches">155254</int>
	    <memory name="brickCacheActualMem" description="Actual memory used by brick caches">
		<peak>13415528</peak>
		<current>524288</current>
	    </memory>
	    <timer name="texture3DBrickmapTime" description="Total brickmap texture3d()">
		<elapsed>0.000000</elapsed>
	    </timer>
	    <timer name="brickCompReadTime" description="Brick compulsory read">
		<elapsed>0.000000</elapsed>
	    </timer>
	    <timer name="brickCapaReadTime" description="Brick capacity read">
		<elapsed>0.000000</elapsed>
	    </timer>
	</stats>
	<stats name="pointclouds" description="Point-based calc. and cache stats" kind="section">
	    <memory name="pointCloudMem" description="Point cloud memory">
		<peak>0</peak>
		<current>0</current>
	    </memory>
	    <memory name="pointOctreeMem" description="Point octree memory">
		<peak>0</peak>
		<current>0</current>
	    </memory>
	    <int name="nReadPoints" description="Points read">0</int>
	    <int name="nPointCacheLookups" description="Point cache lookups">0</int>
	    <int name="nPointCacheHits" description="Point cache hits">0</int>
	    <int name="nPointCacheMisses" description="Point cache misses">0</int>
	    <int name="nPointCacheElems" description="Point cache num slots">3150</int>
	    <memory name="pointCacheActualMem" description="Point cache memory">
		<peak>325104</peak>
		<current>325104</current>
	    </memory>
	    <int name="nReadNodes" description="Octree nodes read">0</int>
	    <int name="nNodeCacheLookups" description="Octree node cache lookups">0</int>
	    <int name="nNodeCacheHits" description="Octree node cache hits">0</int>
	    <int name="nNodeCacheMisses" description="Octree node cache misses">0</int>
	    <int name="nNodeCacheElems" description="Octree node cache num slots">34492</int>
	    <memory name="nodeCacheActualMem" description="Octree node cache memory">
		<peak>3780352</peak>
		<current>3780352</current>
	    </memory>
	    <timer name="texture3DPointcloudTime" description="Total pointcloud texture3d()">
		<elapsed>0.000000</elapsed>
	    </timer>
	    <timer name="getpointsTime" description="Total getpoints()">
		<elapsed>0.000000</elapsed>
	    </timer>
	    <timer name="subsurfaceTime" description="Total subsurface()">
		<elapsed>0.000000</elapsed>
	    </timer>
	    <timer name="occlusionTime" description="Total point-based occlusion()">
		<elapsed>0.000000</elapsed>
	    </timer>
	    <timer name="indirectdiffuseTime" description="Total point-based indirectdiffuse()">
		<elapsed>0.000000</elapsed>
	    </timer>
	    <timer name="cacheReadTime" description="Point/node cache read time">
		<elapsed>0.000000</elapsed>
	    </timer>
	    <timer name="fileReadTime" description="Pointcloud file read time">
		<elapsed>0.000000</elapsed>
	    </timer>
	    <timer name="buildOctreesTime" description="Octrees building time">
		<elapsed>0.000000</elapsed>
	    </timer>
	    <timer name="traverseOctreesTime" description="Octrees traversal time">
		<elapsed>0.000000</elapsed>
	    </timer>
	    <timer name="rasterizeTime" description="Point-based rasterization time">
		<elapsed>0.000000</elapsed>
	    </timer>
	</stats>
	<stats name="system" description="System stats" kind="section">
	    <timer name="totaltime" description="Total time">
		<elapsed>13.322598</elapsed>
		<user>37.906250</user>
		<system>5.093750</system>
	    </timer>
	    <set name="fileLog" description="Files accessed">
		<member>//C|//Program Files/Pixar/RenderManProServer-22.1/lib/plugins//PxrDiffuse</member>
		<member>//C|//Program Files/Pixar/RenderManProServer-22.1/lib/plugins//PxrDiskLight</member>
		<member>//C|//Program Files/Pixar/RenderManProServer-22.1/lib/plugins//PxrLightBxdf</member>
		<member>//C|//Program Files/Pixar/RenderManProServer-22.1/lib/plugins//PxrPathTracer</member>
		<member>//C|//Program Files/Pixar/RenderManProServer-22.1/lib/plugins//PxrPerspective</member>
		<member>//C|//Program Files/Pixar/RenderManProServer-22.1/lib/plugins//PxrSurface</member>
	    </set>
	    <int name="filesOpened" description="Files opened">0</int>
	    <int name="filesReopened" description="Files reopened">0</int>
	    <int name="filesReclaimed" description="Files reclaimed">0</int>
	    <int name="filesOpenError" description="Files not successfully opened">0</int>
	    <string name="osName" description="OS name">Windows</string>
	    <string name="osRelease" description="OS release"/>
	    <string name="osVersion" description="OS version">9200</string>
	    <string name="arch" description="System architecture">Intel64</string>
	    <string name="hostname" description="Host name">LAPTOP-IBDTOIPE</string>
	</stats>
	<stats name="plugins" description="Plugin statistics" kind="section">
	    <timer name="PxrSurface[Chair_Leg_Shader_Pxr]::BeginBxdf" description="PxrSurface[Chair_Leg_Shader_Pxr]::BeginBxdf">
		<elapsed>0.407923</elapsed>
	    </timer>
	    <timer name="PxrSurface[Chair_Plastic_Shader_Pxr]::BeginBxdf" description="PxrSurface[Chair_Plastic_Shader_Pxr]::BeginBxdf">
		<elapsed>0.623041</elapsed>
	    </timer>
	    <int name="PxrSurface Type::Diffuse" description="PxrSurface Type::Diffuse">2</int>
	    <float name="diffuse" description="PxrSurface::diffuse usage">1</float>
	    <float name="specular" description="PxrSurface::specular usage">0</float>
	    <float name="roughSpecular" description="PxrSurface::roughSpecular usage">0</float>
	    <float name="clearcoat" description="PxrSurface::clearcoat usage">0</float>
	    <float name="iridescence" description="PxrSurface::iridescence usage">0</float>
	    <float name="walter" description="PxrSurface::walter usage">0</float>
	    <float name="fuzz" description="PxrSurface::fuzz usage">0</float>
	    <float name="subsurface" description="PxrSurface::subsurface usage">0</float>
	    <float name="singlescatter" description="PxrSurface::singlescatter usage">0</float>
	    <float name="glow" description="PxrSurface::glow usage">0</float>
	    <float name="bump" description="PxrSurface::bump usage">0</float>
	    <float name="interior" description="PxrSurface::interior usage">0</float>
	    <float name="presence" description="PxrSurface::presence usage">0</float>
	    <float name="opacity" description="PxrSurface::opacity usage">0</float>
	    <memory name="pathtracerBufferMemory" description="Pathtracer Buffers">
		<peak>9298835</peak>
		<current>0</current>
	    </memory>
	    <memory name="pathtracerAOVMemory" description="Pathtracer AOVs">
		<peak>0</peak>
		<current>0</current>
	    </memory>
	</stats>
	<stats name="options" description="General Information" kind="section">
	    <string name="copyright">copyright (c) 1988-2018 Pixar.</string>
	    <string name="version">Pixar PhotoRealistic RenderMan 22.1</string>
	    <string name="linkTime">linked Wed Sep 05 20:23:47 2018 Pacific Daylight Time @1890983</string>
	    <string name="build">build windows10_x86-64_vc14icc170_external_release</string>
	    <string name="licenseDigest">  @  @|80i=+20;&lt;T39|EB?@eB8L:W38J&lt;dAA8LWE1GLPD9J&gt;SDE|B98&gt;P50JKVF7GLf2098WC0;8V92&lt;9R62|146=SE2&gt;:Q4369WE9=@X6B:=RE8LKX3B|  F(@@|80i=+20;&lt;T39|EB?@eB8L:W38J&lt;dAA8LWE1GLPD9J&gt;SDE|B98&gt;P50JKVF7GLf2098WC0;8V92&lt;9R62|146=SE2&gt;:Q4369WE9=@X6B:=RE8LKX3B|  F(@@|80i=+20;&lt;T39|EB?@eB8L:W38J&lt;dAA8LWE1GLPD9J&gt;SDE|B98&gt;P50JKVF7GLf2098WC0;8V92&lt;9R62|146=SE2&gt;:Q4369WE9=@X6B:=RE8LKX3B</string>
	    <string name="timestamp">Tue Mar 19 03:07:03 Pacific Daylight Time 2019</string>
	    <int name="threads">6</int>
	    <int name="xRes">327</int>
	    <int name="yRes">715</int>
	    <int name="xSamples">8</int>
	    <int name="ySamples">8</int>
	    <float name="cropLeft">0</float>
	    <float name="cropRight">1</float>
	    <float name="cropTop">0</float>
	    <float name="cropBottom">1</float>
	    <int name="subPixel">0</int>
	    <stats name="displaylist" description="Display list">
		<stats name="display_0" description="Display settings">
		    <string name="name">C:/Users/jakeh/OneDrive/Desktop/CNMNightMarket/images/chair_latest_v001_t01/chair_latest__perspShape_beauty.0001.exr</string>
		    <string name="type">maya</string>
		    <string name="mode">rgba</string>
		    <float name="relativePixelVariance">0</float>
		    <int name="frame">1</int>
		</stats>
	    </stats>
	    <int name="bucketXRes">16</int>
	    <int name="bucketYRes">16</int>
	    <string name="bucketOrder">circle</string>
	    <int name="gridSize">289</int>
	    <int name="textureMemory">4194304</int>
	    <int name="ptextureMemory">1048576</int>
	    <int name="ptextureMaxFiles">128</int>
	    <int name="brickMemory">2097152</int>
	    <int name="octreeMemory">20480</int>
	    <int name="pointMemory">20480</int>
	    <int name="geoCacheMemory">4194304</int>
	    <int name="opacityCacheMemory">2097152</int>
	    <int name="matrixCacheMemory">102400</int>
	    <float name="memoryLimit">0</float>
	    <float name="oThreshR">0.996094</float>
	    <float name="oThreshG">0.996094</float>
	    <float name="oThreshB">0.996094</float>
	    <string name="pixelFilterMode">weighted</string>
	    <int name="minSamples">8</int>
	    <int name="minExtraSamples">8</int>
	    <int name="maxSamples">64</int>
	    <float name="pixelVariance">0.05</float>
	    <float name="darkFalloff">0.025</float>
	    <int name="adaptAll">0</int>
	    <int name="incremental">2</int>
	    <int name="checkpointInterval">0</int>
	    <int name="checkpointExitAt">0</int>
	    <int name="checkpointKeepFiles">0</int>
	    <int name="checkpointAsFinal">0</int>
	</stats>
	<stats name="RIS" description="RIS mode rendering" kind="section">
	    <stats name="ictx" description="RixIntegratorContext" kind="section">
		<int name="sctxCount" description="Number of ShadingCtxs">69</int>
		<int name="msctxCount" description="Number of Mutable ShadingCtxs">0</int>
		<memory name="integratorMem" description="Integrator memory">
		    <peak>1400616</peak>
		    <current>1400616</current>
		</memory>
		<memory name="patternMem" description="Pattern memory">
		    <peak>7336</peak>
		    <current>7336</current>
		</memory>
		<memory name="ictxWaste" description="Waste in memory pools">
		    <peak>1648832</peak>
		    <current>1648832</current>
		</memory>
	    </stats>
	    <stats name="sctx" description="RixShadingContext" kind="section">
		<range name="numPts" description="Shading Points (total)">
		    <current>0</current>
		    <total>1897036</total>
		    <min>0</min>
		    <max>3581</max>
		    <average>24.9131</average>
		    <count>76146</count>
		</range>
		<int name="stcxExecCount" description="Invocations">76146</int>
		<timer name="sctxExecTime" description="Shading Time (total)">
		    <elapsed>1.117750</elapsed>
		</timer>
		<memory name="shadingMem" description="Bxdf memory">
		    <peak>1834680</peak>
		    <current>1743072</current>
		</memory>
	    </stats>
	    <stats name="osctx" description="Overlay RixShadingContext" kind="section">
		<range name="numPts" description="Shading Points (total)">
		    <current>0</current>
		    <total>0</total>
		    <min>0</min>
		    <max>0</max>
		    <average>0</average>
		    <count>0</count>
		</range>
		<int name="stcxExecCount" description="Invocations">0</int>
		<timer name="sctxExecTime" description="Shading Time (total)">
		    <elapsed>0.000000</elapsed>
		</timer>
		<memory name="shadingMem" description="Bxdf memory">
		    <peak>0</peak>
		    <current>0</current>
		</memory>
	    </stats>
	    <stats name="Lighting" description="RixLightingServices" kind="section">
		<int name="nPoints" description="Num points">1897036</int>
		<int name="nInvocations" description="Num invocations (Begin/End or BeginEmission/End)">76146</int>
		<int name="nLightSamples" description="Num light samples">1645409</int>
		<int name="nLightRejectedSamples" description="Num light samples rejection-culled">0</int>
		<int name="nMaterialSamples" description="Num material samples">1645409</int>
		<int name="nMaterialRays" description="Num material sample rays">0</int>
		<int name="nMaterialAreaHits" description="Num material sample hits on area lights">18549</int>
		<int name="nMaterialEnvHits" description="Num material sample hits on env lights">0</int>
		<int name="nMaterialRejectedSamples" description="Num material samples rejection-culled">0</int>
		<int name="mPhotonSamples" description="Num photon samples">0</int>
		<int name="mPhotonHits" description="Num photon sample hits">0</int>
		<timer name="lightingTotalTime" description="Total time in lighting services">
		    <elapsed>6.926077</elapsed>
		</timer>
		<timer name="lightingShadowTime" description="Total time in shadowing">
		    <elapsed>1.471530</elapsed>
		</timer>
		<timer name="lightingInternalTime" description="Total time in lighting services excluding subordinate systems">
		    <elapsed>0.708354</elapsed>
		</timer>
		<timer name="lightingBuildTime" description="Total time building lighting configurations">
		    <elapsed>0.000000</elapsed>
		</timer>
		<timer name="lightingLookupTime" description="Total time looking up lighting configurations">
		    <elapsed>0.000000</elapsed>
		</timer>
		<timer name="lightingMaterialTime" description="Time in material sample evaluation (EvaluateSamples)">
		    <elapsed>0.878570</elapsed>
		</timer>
		<timer name="lightingMaterialShadowTime" description="Time in material sample evaluation - shadowing">
		    <elapsed>0.172164</elapsed>
		</timer>
		<timer name="lightingMaterialTraceTime" description="Time in material sample evaluation - trace">
		    <elapsed>0.395362</elapsed>
		</timer>
		<timer name="lightingMaterialTimeExcluding" description="Time in material sample evaluation excluding subordinate systems">
		    <elapsed>0.138310</elapsed>
		</timer>
		<timer name="lightingLightSampleTime" description="Time in light sample generation (GenerateSamples)">
		    <elapsed>5.339154</elapsed>
		</timer>
		<timer name="lightingLightSamplepickTime" description="Time in light sample generation - pick and sort">
		    <elapsed>0.000000</elapsed>
		</timer>
		<timer name="lightingLightShadowTime" description="Time in light sample generation - shadowing">
		    <elapsed>1.299366</elapsed>
		</timer>
		<timer name="lightingLightEvalTime" description="Time in light sample generation - Bxdf evaluation">
		    <elapsed>0.578520</elapsed>
		</timer>
		<timer name="lightingLightSampleTimeExcluding" description="Time in light sample generation  exlcuding subordinate systems">
		    <elapsed>0.175000</elapsed>
		</timer>
		<timer name="lightingPhotonSampleTime" description="Time in photon generation (GenerateEmission)">
		    <elapsed>0.000000</elapsed>
		</timer>
		<timer name="lightingPhotonSamplepickTime" description="Time in photon generation - pick and sort">
		    <elapsed>0.000000</elapsed>
		</timer>
		<timer name="lightingPhotonTraceBxdfTime" description="Time in photon generation - trace and Bxdf evaluation at hits">
		    <elapsed>0.000000</elapsed>
		</timer>
		<timer name="lightingPhotonSampleTimeExcluding" description="Time in photon generation excluding subordinate systems">
		    <elapsed>0.000000</elapsed>
		</timer>
		<memory name="lightingMem" description="Memory consumed by lighting services">
		    <peak>872363</peak>
		    <current>658091</current>
		</memory>
		<memory name="estimatorLightingMem" description="Memory consumed by lighting services for estimators">
		    <peak>0</peak>
		    <current>0</current>
		</memory>
		<memory name="estimatorSampleMem" description="Memory consumed by estimator samples">
		    <peak>0</peak>
		    <current>0</current>
		</memory>
		<memory name="estimatorReceiverMem" description="Memory consumed by estimators">
		    <peak>0</peak>
		    <current>0</current>
		</memory>
		<memory name="estimatorEmitterMem" description="Memory consumed by emitter groupings">
		    <peak>0</peak>
		    <current>0</current>
		</memory>
		<memory name="estimatorTreeMem" description="Memory consumed by estimator trees">
		    <peak>0</peak>
		    <current>0</current>
		</memory>
		<int name="estimatorCount" description="Number of estimators">0</int>
		<memory name="lightingCdfMem" description="Memory consumed by cdf structures">
		    <peak>0</peak>
		    <current>0</current>
		</memory>
		<memory name="lightingPdfMem" description="Memory consumed by pdf structures">
		    <peak>0</peak>
		    <current>0</current>
		</memory>
		<memory name="lightingSampleMem" description="Memory consumed by sample records">
		    <peak>0</peak>
		    <current>0</current>
		</memory>
		<memory name="lightingTransientMem" description="Memory consumed by transient structures">
		    <peak>0</peak>
		    <current>0</current>
		</memory>
		<memory name="lightingDbMem" description="Memory consumed by lighting database">
		    <peak>0</peak>
		    <current>0</current>
		</memory>
		<int name="lightingDbNPatches" description="Num patches in lighting database">0</int>
		<int name="lightingServicesInstances" description="Num unique lighting configurations">0</int>
		<int name="lightingShadowGrops" description="Num unique shadowing groups">0</int>
		<timer name="lightingLightSampleTraceLightTime" description="Time to trace light samples against lighting db">
		    <elapsed>0.000000</elapsed>
		</timer>
		<timer name="lightingLightSampleSelectEvalTime" description="Time to compute a selected light&apos;s probability of being chosen">
		    <elapsed>0.000000</elapsed>
		</timer>
		<timer name="lightingMaterialSelectEvalTime" description="Time to compute an intersected light&apos;s probability of being chosen">
		    <elapsed>0.172734</elapsed>
		</timer>
		<timer name="lightingLightSampleSelectTime" description="Time to select a light">
		    <elapsed>3.286267</elapsed>
		</timer>
		<timer name="lightingLightSelectBeginTime" description="Time to prepare for light selection">
		    <elapsed>0.671498</elapsed>
		</timer>
	    </stats>
	    <stats name="plugins" description="Plugins" kind="section">
		<stats name="integrator" description="Integrator" kind="section">
		    <stats name="PxrPathTracer" description="PxrPathTracer" kind="section">
<stats name="parameters" description="parameters" >
<int name="numLightSamples"> 1 </int>
<int name="numBxdfSamples"> 1 </int>
<int name="numIndirectSamples"> 1 </int>
<int name="numDiffuseSamples"> 1 </int>
<int name="numSpecularSamples"> 1 </int>
<int name="numSubsurfaceSamples"> 1 </int>
<int name="numRefractionSamples"> 1 </int>
<string name="sampleMode"> Bxdf </string>
<int name="rouletteDepth"> 4 </int>
<float name="rouletteThreshold"> 0.200000 </float>
<int name="clampDepth"> 2 </int>
<float name="clampLuminance"> 10.000000 </float>
<int name="allowCaustics"> 0 </int>
<int name="maxPathLength"> 9 </int>
<int name="accumOpacity"> 0 </int>
<int name="maxContinuationLength"> 256 </int>
</stats>
<histogram name="pathDepthTimer" description="Ray Depth Timer (sec)">
<bin label="1">21.172125</bin>
<bin label="2">1.137726</bin>
<bin label="3">0.000000</bin>
<bin label="4">0.000000</bin>
<bin label="5">0.000000</bin>
<bin label="6">0.000000</bin>
<bin label="7">0.000000</bin>
<bin label="8">0.000000</bin>
<bin label="9">0.000000</bin>
<bin label="10">0.000000</bin>
</histogram>
<histogram name="pathRayCounts" description="Ray Count at Depth">
<bin label="1">18560270</bin>
<bin label="2">0</bin>
<bin label="3">0</bin>
<bin label="4">0</bin>
<bin label="5">0</bin>
<bin label="6">0</bin>
<bin label="7">0</bin>
<bin label="8">0</bin>
<bin label="9">0</bin>
<bin label="10">0</bin>
</histogram>

		    </stats>
		</stats>
		<stats name="bxdfs" description="Bxdfs" kind="section">
		    <stats name="PxrDiffuse" description="PxrDiffuse" kind="bxdf">
			<int name="NumBeginBxdf" description="">0</int>
			<timer name="BeginBxdfTime" description="">
			    <elapsed>0.000000</elapsed>
			</timer>
			<int name="NumBeginOpacity" description="">0</int>
			<int name="NumInteriorVolume" description="">0</int>
			<int name="NumExteriorVolume" description="">0</int>
			<int name="NumTransmissionVolume" description="">0</int>
			<int name="NumVolumeSampling" description="">0</int>
			<timer name="BeginOpacityTime" description="">
			    <elapsed>0.000000</elapsed>
			</timer>
			<int name="NumBeginVolume" description="">0</int>
			<timer name="BeginVolumeTime" description="">
			    <elapsed>0.000000</elapsed>
			</timer>
			<int name="NumBeginSubsurface" description="">0</int>
			<timer name="BeginSubsurfaceTime" description="">
			    <elapsed>0.000000</elapsed>
			</timer>
			<timer name="VolumeSamplingTime" description="">
			    <elapsed>0.000000</elapsed>
			</timer>
		    </stats>
		    <stats name="PxrLightBxdf" description="PxrLightBxdf" kind="bxdf">
			<int name="NumBeginBxdf" description="">0</int>
			<timer name="BeginBxdfTime" description="">
			    <elapsed>0.000000</elapsed>
			</timer>
			<int name="NumBeginOpacity" description="">0</int>
			<int name="NumInteriorVolume" description="">0</int>
			<int name="NumExteriorVolume" description="">0</int>
			<int name="NumTransmissionVolume" description="">0</int>
			<int name="NumVolumeSampling" description="">0</int>
			<timer name="BeginOpacityTime" description="">
			    <elapsed>0.000000</elapsed>
			</timer>
			<int name="NumBeginVolume" description="">0</int>
			<timer name="BeginVolumeTime" description="">
			    <elapsed>0.000000</elapsed>
			</timer>
			<int name="NumBeginSubsurface" description="">0</int>
			<timer name="BeginSubsurfaceTime" description="">
			    <elapsed>0.000000</elapsed>
			</timer>
			<timer name="VolumeSamplingTime" description="">
			    <elapsed>0.000000</elapsed>
			</timer>
		    </stats>
		    <stats name="PxrSurface" description="PxrSurface" kind="bxdf">
			<int name="NumBeginBxdf" description="">76146</int>
			<timer name="BeginBxdfTime" description="">
			    <elapsed>1.056952</elapsed>
			</timer>
			<int name="NumBeginOpacity" description="">0</int>
			<int name="NumInteriorVolume" description="">0</int>
			<int name="NumExteriorVolume" description="">0</int>
			<int name="NumTransmissionVolume" description="">0</int>
			<int name="NumVolumeSampling" description="">0</int>
			<timer name="BeginOpacityTime" description="">
			    <elapsed>0.000000</elapsed>
			</timer>
			<int name="NumBeginVolume" description="">0</int>
			<timer name="BeginVolumeTime" description="">
			    <elapsed>0.000000</elapsed>
			</timer>
			<int name="NumBeginSubsurface" description="">0</int>
			<timer name="BeginSubsurfaceTime" description="">
			    <elapsed>0.000000</elapsed>
			</timer>
			<timer name="VolumeSamplingTime" description="">
			    <elapsed>0.000000</elapsed>
			</timer>
		    </stats>
		</stats>
		<stats name="patterns" description="Patterns" kind="section">
		</stats>
	    </stats>
	    <stats name="RISNodes" description="characteristics of your scene&apos;s use of RIS nodes">
		<stats name="Bxdf" description="Time and memory associated with Bxdf">
		    <memory name="memory" description="memory">
			<peak>11560</peak>
			<current>11560</current>
			<total>11560</total>
			<count>5</count>
		    </memory>
		    <timer name="creationTime" description="creationTime">
			<elapsed>0.003573</elapsed>
		    </timer>
		</stats>
		<stats name="Pattern" description="Time and memory used by Pattern">
		    <memory name="memory" description="memory">
			<peak>0</peak>
			<current>0</current>
			<total>0</total>
			<count>0</count>
		    </memory>
		    <timer name="creationTime" description="creationTime">
			<elapsed>0.000000</elapsed>
		    </timer>
		</stats>
		<stats name="Other" description="Time and memory used by other RixShadingPlugin">
		    <memory name="memory" description="memory">
			<peak>2576</peak>
			<current>2576</current>
			<total>2576</total>
			<count>2</count>
		    </memory>
		    <timer name="creationTime" description="creationTime">
			<elapsed>0.001657</elapsed>
		    </timer>
		</stats>
	    </stats>
	    <stats name="rayHider" description="Raytrace Hider" kind="section">
		<memory name="framebufferMem" description="Framebuffer and display memory">
		    <peak>21912963</peak>
		    <current>140163</current>
		</memory>
		<float name="adaptSkipped" description="Adaptive sampling fraction skipped">0.76345</float>
		<histogram name="adaptActive" description="Average active pixels by increment">
		    <bin label="1">4010181</bin>
		    <bin label="2">471786</bin>
		    <bin label="3">471786</bin>
		    <bin label="4">471786</bin>
		    <bin label="5">471786</bin>
		    <bin label="6">471786</bin>
		    <bin label="7">471786</bin>
		    <bin label="8">471786</bin>
		    <bin label="9">36677</bin>
		    <bin label="10">35793</bin>
		    <bin label="11">32086</bin>
		    <bin label="12">28766</bin>
		    <bin label="13">25915</bin>
		    <bin label="14">23950</bin>
		    <bin label="15">22085</bin>
		    <bin label="16">20363</bin>
		    <bin label="17">18941</bin>
		    <bin label="18">17645</bin>
		    <bin label="19">16668</bin>
		    <bin label="20">15850</bin>
		    <bin label="21">15224</bin>
		    <bin label="22">14017</bin>
		    <bin label="23">10538</bin>
		    <bin label="24">9312</bin>
		    <bin label="25">9067</bin>
		    <bin label="26">8633</bin>
		    <bin label="27">8228</bin>
		    <bin label="28">7733</bin>
		    <bin label="29">5702</bin>
		    <bin label="30">3728</bin>
		    <bin label="31">3521</bin>
		    <bin label="32">3440</bin>
		    <bin label="33">3284</bin>
		    <bin label="34">3108</bin>
		    <bin label="35">2952</bin>
		    <bin label="36">2847</bin>
		    <bin label="37">2683</bin>
		    <bin label="38">2474</bin>
		    <bin label="39">2251</bin>
		    <bin label="40">2118</bin>
		    <bin label="41">1983</bin>
		    <bin label="42">1770</bin>
		    <bin label="43">1560</bin>
		    <bin label="44">1402</bin>
		    <bin label="45">1276</bin>
		    <bin label="46">1093</bin>
		    <bin label="47">912</bin>
		    <bin label="48">785</bin>
		    <bin label="49">671</bin>
		    <bin label="50">580</bin>
		    <bin label="51">436</bin>
		    <bin label="52">330</bin>
		    <bin label="53">270</bin>
		    <bin label="54">195</bin>
		    <bin label="55">132</bin>
		    <bin label="56">96</bin>
		    <bin label="57">90</bin>
		    <bin label="58">63</bin>
		    <bin label="59">15</bin>
		    <bin label="60">15</bin>
		</histogram>
		<FloatMap2D name="adaptMap" description="adaptMap">
		    <int name="width" description="width">21</int>
		    <int name="height" description="height">45</int>
		    <float name="min" description="min">31.000000</float>
		    <float name="max" description="max">58.347656</float>
		    <float name="avg" description="avg">32.774442</float>
		    <FloatArray name="values" description="values">
			<el>0.000000</el>
			<el>0.000000</el>
			<el>0.000000</el>
			<el>0.000000</el>
			<el>0.000000</el>
			<el>0.000000</el>
			<el>0.000000</el>
			<el>0.000000</el>
			<el>0.000000</el>
			<el>0.000000</el>
			<el>0.000000</el>
			<el>0.000000</el>
			<el>0.000000</el>
			<el>0.000000</el>
			<el>0.000000</el>
			<el>0.000000</el>
			<el>0.000000</el>
			<el>0.000000</el>
			<el>0.000000</el>
			<el>0.000000</el>
			<el>0.000000</el>
			<el>0.000000</el>
			<el>0.000000</el>
			<el>0.000000</el>
			<el>0.000000</el>
			<el>0.000000</el>
			<el>0.000000</el>
			<el>0.000000</el>
			<el>0.000000</el>
			<el>0.000000</el>
			<el>0.000000</el>
			<el>0.000000</el>
			<el>0.000000</el>
			<el>0.000000</el>
			<el>0.000000</el>
			<el>0.000000</el>
			<el>0.000000</el>
			<el>0.000000</el>
			<el>0.000000</el>
			<el>0.000000</el>
			<el>0.000000</el>
			<el>0.000000</el>
			<el>0.000000</el>
			<el>0.000000</el>
			<el>0.000000</el>
			<el>0.000000</el>
			<el>0.000000</el>
			<el>0.000000</el>
			<el>0.000000</el>
			<el>0.000000</el>
			<el>0.000000</el>
			<el>0.000000</el>
			<el>0.000000</el>
			<el>0.000000</el>
			<el>0.000000</el>
			<el>0.000000</el>
			<el>0.000000</el>
			<el>0.000000</el>
			<el>0.000000</el>
			<el>0.000000</el>
			<el>0.000000</el>
			<el>0.000000</el>
			<el>0.000000</el>
			<el>0.000000</el>
			<el>0.000000</el>
			<el>0.000000</el>
			<el>0.000000</el>
			<el>0.000000</el>
			<el>0.000000</el>
			<el>0.000000</el>
			<el>0.000000</el>
			<el>0.000000</el>
			<el>0.000000</el>
			<el>0.000000</el>
			<el>0.000000</el>
			<el>0.000000</el>
			<el>0.000000</el>
			<el>0.000000</el>
			<el>0.000000</el>
			<el>0.000000</el>
			<el>0.000000</el>
			<el>0.000000</el>
			<el>0.000000</el>
			<el>0.000000</el>
			<el>0.000000</el>
			<el>0.000000</el>
			<el>0.000000</el>
			<el>0.000000</el>
			<el>0.000000</el>
			<el>0.000000</el>
			<el>0.000000</el>
			<el>0.000000</el>
			<el>0.000000</el>
			<el>0.000000</el>
			<el>0.000000</el>
			<el>0.000000</el>
			<el>0.000000</el>
			<el>0.000000</el>
			<el>0.000000</el>
			<el>0.000000</el>
			<el>0.000000</el>
			<el>0.000000</el>
			<el>0.000000</el>
			<el>0.000000</el>
			<el>0.000000</el>
			<el>0.000000</el>
			<el>0.000000</el>
			<el>0.000000</el>
			<el>0.000000</el>
			<el>0.000000</el>
			<el>0.000000</el>
			<el>0.000000</el>
			<el>0.000000</el>
			<el>0.000000</el>
			<el>0.000000</el>
			<el>0.000000</el>
			<el>0.000000</el>
			<el>0.000000</el>
			<el>0.000000</el>
			<el>0.000000</el>
			<el>0.000000</el>
			<el>0.000000</el>
			<el>0.000000</el>
			<el>0.000000</el>
			<el>0.000000</el>
			<el>0.000000</el>
			<el>0.000000</el>
			<el>0.000000</el>
			<el>0.000000</el>
			<el>0.000000</el>
			<el>0.000000</el>
			<el>0.000000</el>
			<el>0.000000</el>
			<el>0.000000</el>
			<el>0.000000</el>
			<el>0.000000</el>
			<el>0.000000</el>
			<el>0.000000</el>
			<el>0.000000</el>
			<el>0.000000</el>
			<el>0.000000</el>
			<el>0.000000</el>
			<el>0.000000</el>
			<el>0.000000</el>
			<el>0.000000</el>
			<el>0.000000</el>
			<el>0.000000</el>
			<el>0.000000</el>
			<el>0.000000</el>
			<el>0.000000</el>
			<el>0.000000</el>
			<el>0.000000</el>
			<el>0.000000</el>
			<el>0.000000</el>
			<el>0.000000</el>
			<el>0.000000</el>
			<el>0.000000</el>
			<el>0.000000</el>
			<el>0.000000</el>
			<el>0.000000</el>
			<el>0.000000</el>
			<el>0.000000</el>
			<el>0.000000</el>
			<el>0.000000</el>
			<el>0.000000</el>
			<el>0.000000</el>
			<el>0.000000</el>
			<el>0.000000</el>
			<el>0.000000</el>
			<el>0.000000</el>
			<el>0.000000</el>
			<el>0.000000</el>
			<el>0.000000</el>
			<el>0.000000</el>
			<el>0.000000</el>
			<el>0.000000</el>
			<el>0.000000</el>
			<el>0.000000</el>
			<el>0.000000</el>
			<el>0.000000</el>
			<el>0.000000</el>
			<el>0.000000</el>
			<el>0.000000</el>
			<el>0.000000</el>
			<el>0.000000</el>
			<el>0.000000</el>
			<el>0.000000</el>
			<el>0.000000</el>
			<el>0.000000</el>
			<el>0.000000</el>
			<el>0.000000</el>
			<el>0.000000</el>
			<el>0.000000</el>
			<el>0.000000</el>
			<el>0.000000</el>
			<el>0.000000</el>
			<el>0.000000</el>
			<el>0.000000</el>
			<el>0.000000</el>
			<el>0.000000</el>
			<el>0.000000</el>
			<el>0.000000</el>
			<el>0.000000</el>
			<el>0.000000</el>
			<el>0.000000</el>
			<el>0.000000</el>
			<el>0.000000</el>
			<el>0.000000</el>
			<el>0.000000</el>
			<el>0.000000</el>
			<el>0.000000</el>
			<el>0.000000</el>
			<el>0.000000</el>
			<el>0.000000</el>
			<el>0.000000</el>
			<el>0.000000</el>
			<el>0.000000</el>
			<el>0.000000</el>
			<el>0.000000</el>
			<el>0.000000</el>
			<el>0.000000</el>
			<el>0.000000</el>
			<el>0.000000</el>
			<el>0.000000</el>
			<el>0.000000</el>
			<el>0.000000</el>
			<el>0.000000</el>
			<el>0.000000</el>
			<el>0.000000</el>
			<el>0.000000</el>
			<el>0.000000</el>
			<el>0.000000</el>
			<el>0.000000</el>
			<el>0.000000</el>
			<el>0.000000</el>
			<el>0.000000</el>
			<el>0.000000</el>
			<el>0.000000</el>
			<el>0.000000</el>
			<el>0.000000</el>
			<el>0.000000</el>
			<el>0.000000</el>
			<el>0.000000</el>
			<el>0.000000</el>
			<el>0.000000</el>
			<el>0.000000</el>
			<el>0.000000</el>
			<el>0.000000</el>
			<el>0.000000</el>
			<el>0.000000</el>
			<el>0.000000</el>
			<el>0.000000</el>
			<el>0.000000</el>
			<el>0.000000</el>
			<el>0.000000</el>
			<el>0.000000</el>
			<el>0.000000</el>
			<el>0.000000</el>
			<el>0.000000</el>
			<el>0.000000</el>
			<el>0.000000</el>
			<el>0.000000</el>
			<el>0.000000</el>
			<el>0.000000</el>
			<el>0.000000</el>
			<el>0.000000</el>
			<el>0.000000</el>
			<el>0.000000</el>
			<el>0.000000</el>
			<el>0.000000</el>
			<el>0.000000</el>
			<el>0.000000</el>
			<el>0.000000</el>
			<el>0.000000</el>
			<el>0.000000</el>
			<el>0.000000</el>
			<el>0.000000</el>
			<el>0.000000</el>
			<el>0.000000</el>
			<el>0.000000</el>
			<el>0.000000</el>
			<el>0.000000</el>
			<el>0.000000</el>
			<el>0.000000</el>
			<el>0.000000</el>
			<el>0.000000</el>
			<el>0.000000</el>
			<el>0.000000</el>
			<el>0.000000</el>
			<el>0.000000</el>
			<el>0.000000</el>
			<el>0.000000</el>
			<el>0.000000</el>
			<el>0.000000</el>
			<el>0.000000</el>
			<el>0.000000</el>
			<el>0.000000</el>
			<el>0.000000</el>
			<el>0.000000</el>
			<el>0.000000</el>
			<el>0.000000</el>
			<el>0.138980</el>
			<el>0.380231</el>
			<el>0.404799</el>
			<el>0.448936</el>
			<el>0.380803</el>
			<el>0.409084</el>
			<el>0.439366</el>
			<el>0.049707</el>
			<el>0.000000</el>
			<el>0.000000</el>
			<el>0.000000</el>
			<el>0.000000</el>
			<el>0.000000</el>
			<el>0.000000</el>
			<el>0.000000</el>
			<el>0.000000</el>
			<el>0.000000</el>
			<el>0.000000</el>
			<el>0.000000</el>
			<el>0.000000</el>
			<el>0.179689</el>
			<el>0.536638</el>
			<el>0.359234</el>
			<el>0.432795</el>
			<el>0.459791</el>
			<el>0.459934</el>
			<el>0.444079</el>
			<el>0.375089</el>
			<el>0.441080</el>
			<el>0.000000</el>
			<el>0.000000</el>
			<el>0.000000</el>
			<el>0.000000</el>
			<el>0.000000</el>
			<el>0.000000</el>
			<el>0.000000</el>
			<el>0.000000</el>
			<el>0.000000</el>
			<el>0.000000</el>
			<el>0.000000</el>
			<el>0.000000</el>
			<el>0.392373</el>
			<el>0.304385</el>
			<el>0.406371</el>
			<el>0.442937</el>
			<el>0.452935</el>
			<el>0.440223</el>
			<el>0.393230</el>
			<el>0.328239</el>
			<el>0.349807</el>
			<el>0.000000</el>
			<el>0.000000</el>
			<el>0.000000</el>
			<el>0.000000</el>
			<el>0.000000</el>
			<el>0.000000</el>
			<el>0.000000</el>
			<el>0.000000</el>
			<el>0.000000</el>
			<el>0.000000</el>
			<el>0.000000</el>
			<el>0.000000</el>
			<el>0.458363</el>
			<el>0.317240</el>
			<el>0.378375</el>
			<el>0.405799</el>
			<el>0.434795</el>
			<el>0.370518</el>
			<el>0.365662</el>
			<el>0.290101</el>
			<el>0.317812</el>
			<el>0.000000</el>
			<el>0.000000</el>
			<el>0.000000</el>
			<el>0.000000</el>
			<el>0.000000</el>
			<el>0.000000</el>
			<el>0.000000</el>
			<el>0.000000</el>
			<el>0.000000</el>
			<el>0.000000</el>
			<el>0.000000</el>
			<el>0.000000</el>
			<el>0.684759</el>
			<el>0.385659</el>
			<el>0.352664</el>
			<el>0.436366</el>
			<el>0.342808</el>
			<el>0.476932</el>
			<el>0.500214</el>
			<el>0.655478</el>
			<el>0.056278</el>
			<el>0.000000</el>
			<el>0.000000</el>
			<el>0.000000</el>
			<el>0.000000</el>
			<el>0.000000</el>
			<el>0.000000</el>
			<el>0.000000</el>
			<el>0.000000</el>
			<el>0.000000</el>
			<el>0.000000</el>
			<el>0.000000</el>
			<el>0.000000</el>
			<el>0.735038</el>
			<el>0.000000</el>
			<el>0.000000</el>
			<el>0.000000</el>
			<el>0.000000</el>
			<el>0.000000</el>
			<el>0.000000</el>
			<el>0.667048</el>
			<el>0.000000</el>
			<el>0.000000</el>
			<el>0.000000</el>
			<el>0.000000</el>
			<el>0.000000</el>
			<el>0.000000</el>
			<el>0.000000</el>
			<el>0.000000</el>
			<el>0.000000</el>
			<el>0.000000</el>
			<el>0.000000</el>
			<el>0.000000</el>
			<el>0.102700</el>
			<el>0.649050</el>
			<el>0.000000</el>
			<el>0.000000</el>
			<el>0.000000</el>
			<el>0.000000</el>
			<el>0.000000</el>
			<el>0.091130</el>
			<el>0.547208</el>
			<el>0.000000</el>
			<el>0.000000</el>
			<el>0.000000</el>
			<el>0.000000</el>
			<el>0.000000</el>
			<el>0.000000</el>
			<el>0.000000</el>
			<el>0.000000</el>
			<el>0.000000</el>
			<el>0.000000</el>
			<el>0.000000</el>
			<el>0.000000</el>
			<el>0.344379</el>
			<el>0.954435</el>
			<el>0.078846</el>
			<el>0.000857</el>
			<el>0.000000</el>
			<el>0.000000</el>
			<el>0.000000</el>
			<el>0.313241</el>
			<el>0.264105</el>
			<el>0.000000</el>
			<el>0.000000</el>
			<el>0.000000</el>
			<el>0.000000</el>
			<el>0.000000</el>
			<el>0.000000</el>
			<el>0.000000</el>
			<el>0.000000</el>
			<el>0.000000</el>
			<el>0.000000</el>
			<el>0.000000</el>
			<el>0.000000</el>
			<el>0.518212</el>
			<el>0.781174</el>
			<el>0.472790</el>
			<el>0.437509</el>
			<el>0.431224</el>
			<el>0.405513</el>
			<el>0.406228</el>
			<el>0.451078</el>
			<el>0.247679</el>
			<el>0.000000</el>
			<el>0.000000</el>
			<el>0.000000</el>
			<el>0.000000</el>
			<el>0.000000</el>
			<el>0.000000</el>
			<el>0.000000</el>
			<el>0.000000</el>
			<el>0.000000</el>
			<el>0.000000</el>
			<el>0.007999</el>
			<el>0.486788</el>
			<el>0.543922</el>
			<el>0.335809</el>
			<el>0.249536</el>
			<el>0.238966</el>
			<el>0.252821</el>
			<el>0.182688</el>
			<el>0.203542</el>
			<el>0.141123</el>
			<el>0.348950</el>
			<el>0.000000</el>
			<el>0.000000</el>
			<el>0.000000</el>
			<el>0.000000</el>
			<el>0.000000</el>
			<el>0.000000</el>
			<el>0.000000</el>
			<el>0.000000</el>
			<el>0.000000</el>
			<el>0.000000</el>
			<el>0.411513</el>
			<el>0.180117</el>
			<el>0.240680</el>
			<el>0.283245</el>
			<el>0.299814</el>
			<el>0.457792</el>
			<el>0.411227</el>
			<el>0.404656</el>
			<el>0.176118</el>
			<el>0.698043</el>
			<el>0.441651</el>
			<el>0.000000</el>
			<el>0.000000</el>
			<el>0.000000</el>
			<el>0.000000</el>
			<el>0.000000</el>
			<el>0.000000</el>
			<el>0.000000</el>
			<el>0.000000</el>
			<el>0.000000</el>
			<el>0.000000</el>
			<el>0.178974</el>
			<el>0.547208</el>
			<el>0.464648</el>
			<el>0.355235</el>
			<el>0.380946</el>
			<el>0.190973</el>
			<el>0.117555</el>
			<el>0.122268</el>
			<el>0.588916</el>
			<el>0.890016</el>
			<el>0.428225</el>
			<el>0.000000</el>
			<el>0.000000</el>
			<el>0.000000</el>
			<el>0.000000</el>
			<el>0.000000</el>
			<el>0.000000</el>
			<el>0.000000</el>
			<el>0.000000</el>
			<el>0.000000</el>
			<el>0.000000</el>
			<el>0.000000</el>
			<el>0.394658</el>
			<el>0.335523</el>
			<el>0.000000</el>
			<el>0.956578</el>
			<el>0.935723</el>
			<el>1.000000</el>
			<el>0.711898</el>
			<el>0.135266</el>
			<el>0.674189</el>
			<el>0.436223</el>
			<el>0.000000</el>
			<el>0.000000</el>
			<el>0.000000</el>
			<el>0.000000</el>
			<el>0.000000</el>
			<el>0.000000</el>
			<el>0.000000</el>
			<el>0.000000</el>
			<el>0.000000</el>
			<el>0.000000</el>
			<el>0.000000</el>
			<el>0.691044</el>
			<el>0.087987</el>
			<el>0.000000</el>
			<el>0.692473</el>
			<el>0.000000</el>
			<el>0.047993</el>
			<el>0.336238</el>
			<el>0.768747</el>
			<el>0.764319</el>
			<el>0.454506</el>
			<el>0.000000</el>
			<el>0.000000</el>
			<el>0.000000</el>
			<el>0.000000</el>
			<el>0.000000</el>
			<el>0.000000</el>
			<el>0.000000</el>
			<el>0.000000</el>
			<el>0.000000</el>
			<el>0.000000</el>
			<el>0.000000</el>
			<el>0.810027</el>
			<el>0.320526</el>
			<el>0.017283</el>
			<el>0.418083</el>
			<el>0.000000</el>
			<el>0.000000</el>
			<el>0.000000</el>
			<el>0.348379</el>
			<el>0.342380</el>
			<el>0.536780</el>
			<el>0.000000</el>
			<el>0.000000</el>
			<el>0.000000</el>
			<el>0.000000</el>
			<el>0.000000</el>
			<el>0.000000</el>
			<el>0.000000</el>
			<el>0.000000</el>
			<el>0.000000</el>
			<el>0.000000</el>
			<el>0.057849</el>
			<el>0.740751</el>
			<el>0.453364</el>
			<el>0.695758</el>
			<el>0.704614</el>
			<el>0.541923</el>
			<el>0.214255</el>
			<el>0.000000</el>
			<el>0.419369</el>
			<el>0.347236</el>
			<el>0.578774</el>
			<el>0.000000</el>
			<el>0.000000</el>
			<el>0.000000</el>
			<el>0.000000</el>
			<el>0.000000</el>
			<el>0.000000</el>
			<el>0.000000</el>
			<el>0.000000</el>
			<el>0.000000</el>
			<el>0.000000</el>
			<el>0.313384</el>
			<el>0.372947</el>
			<el>0.000000</el>
			<el>0.000000</el>
			<el>0.000000</el>
			<el>0.226682</el>
			<el>0.522640</el>
			<el>0.752607</el>
			<el>0.889302</el>
			<el>0.048136</el>
			<el>0.000000</el>
			<el>0.000000</el>
			<el>0.000000</el>
			<el>0.000000</el>
			<el>0.000000</el>
			<el>0.000000</el>
			<el>0.000000</el>
			<el>0.000000</el>
			<el>0.000000</el>
			<el>0.000000</el>
			<el>0.000000</el>
			<el>0.375089</el>
			<el>0.382660</el>
			<el>0.000000</el>
			<el>0.000000</el>
			<el>0.000000</el>
			<el>0.000000</el>
			<el>0.000000</el>
			<el>0.000000</el>
			<el>0.682617</el>
			<el>0.000000</el>
			<el>0.000000</el>
			<el>0.000000</el>
			<el>0.000000</el>
			<el>0.000000</el>
			<el>0.000000</el>
			<el>0.000000</el>
			<el>0.000000</el>
			<el>0.000000</el>
			<el>0.000000</el>
			<el>0.000000</el>
			<el>0.000000</el>
			<el>0.286102</el>
			<el>0.081560</el>
			<el>0.000000</el>
			<el>0.000000</el>
			<el>0.000000</el>
			<el>0.000000</el>
			<el>0.000000</el>
			<el>0.000000</el>
			<el>0.693330</el>
			<el>0.000000</el>
			<el>0.000000</el>
			<el>0.000000</el>
			<el>0.000000</el>
			<el>0.000000</el>
			<el>0.000000</el>
			<el>0.000000</el>
			<el>0.000000</el>
			<el>0.000000</el>
			<el>0.000000</el>
			<el>0.000000</el>
			<el>0.000000</el>
			<el>0.000000</el>
			<el>0.000000</el>
			<el>0.000000</el>
			<el>0.000000</el>
			<el>0.000000</el>
			<el>0.000000</el>
			<el>0.000000</el>
			<el>0.222825</el>
			<el>0.512355</el>
			<el>0.000000</el>
			<el>0.000000</el>
			<el>0.000000</el>
			<el>0.000000</el>
			<el>0.000000</el>
			<el>0.000000</el>
			<el>0.000000</el>
			<el>0.000000</el>
			<el>0.000000</el>
			<el>0.000000</el>
			<el>0.000000</el>
			<el>0.000000</el>
			<el>0.000000</el>
			<el>0.000000</el>
			<el>0.000000</el>
			<el>0.000000</el>
			<el>0.000000</el>
			<el>0.000000</el>
			<el>0.000000</el>
			<el>0.346379</el>
			<el>0.394658</el>
			<el>0.000000</el>
			<el>0.000000</el>
			<el>0.000000</el>
			<el>0.000000</el>
			<el>0.000000</el>
			<el>0.000000</el>
			<el>0.000000</el>
			<el>0.000000</el>
			<el>0.000000</el>
			<el>0.000000</el>
			<el>0.000000</el>
			<el>0.000000</el>
			<el>0.000000</el>
			<el>0.000000</el>
			<el>0.000000</el>
			<el>0.000000</el>
			<el>0.000000</el>
			<el>0.000000</el>
			<el>0.000000</el>
			<el>0.000000</el>
			<el>0.000000</el>
			<el>0.000000</el>
			<el>0.000000</el>
			<el>0.000000</el>
			<el>0.000000</el>
			<el>0.000000</el>
			<el>0.000000</el>
			<el>0.000000</el>
			<el>0.000000</el>
			<el>0.000000</el>
			<el>0.000000</el>
			<el>0.000000</el>
			<el>0.000000</el>
			<el>0.000000</el>
			<el>0.000000</el>
			<el>0.000000</el>
			<el>0.000000</el>
			<el>0.000000</el>
			<el>0.000000</el>
			<el>0.000000</el>
			<el>0.000000</el>
			<el>0.000000</el>
			<el>0.000000</el>
			<el>0.000000</el>
			<el>0.000000</el>
			<el>0.000000</el>
			<el>0.000000</el>
			<el>0.000000</el>
			<el>0.000000</el>
			<el>0.000000</el>
			<el>0.000000</el>
			<el>0.000000</el>
			<el>0.000000</el>
			<el>0.000000</el>
			<el>0.000000</el>
			<el>0.000000</el>
			<el>0.000000</el>
			<el>0.000000</el>
			<el>0.000000</el>
			<el>0.000000</el>
			<el>0.000000</el>
			<el>0.000000</el>
			<el>0.000000</el>
			<el>0.000000</el>
			<el>0.000000</el>
			<el>0.000000</el>
			<el>0.000000</el>
			<el>0.000000</el>
			<el>0.000000</el>
			<el>0.000000</el>
			<el>0.000000</el>
			<el>0.000000</el>
			<el>0.000000</el>
			<el>0.000000</el>
			<el>0.000000</el>
			<el>0.000000</el>
			<el>0.000000</el>
			<el>0.000000</el>
			<el>0.000000</el>
			<el>0.000000</el>
			<el>0.000000</el>
			<el>0.000000</el>
			<el>0.000000</el>
			<el>0.000000</el>
			<el>0.000000</el>
			<el>0.000000</el>
			<el>0.000000</el>
			<el>0.000000</el>
			<el>0.000000</el>
			<el>0.000000</el>
			<el>0.000000</el>
			<el>0.000000</el>
			<el>0.000000</el>
			<el>0.000000</el>
			<el>0.000000</el>
			<el>0.000000</el>
			<el>0.000000</el>
			<el>0.000000</el>
			<el>0.000000</el>
			<el>0.000000</el>
			<el>0.000000</el>
			<el>0.000000</el>
			<el>0.000000</el>
			<el>0.000000</el>
			<el>0.000000</el>
			<el>0.000000</el>
			<el>0.000000</el>
			<el>0.000000</el>
			<el>0.000000</el>
			<el>0.000000</el>
			<el>0.000000</el>
			<el>0.000000</el>
			<el>0.000000</el>
			<el>0.000000</el>
			<el>0.000000</el>
			<el>0.000000</el>
			<el>0.000000</el>
			<el>0.000000</el>
			<el>0.000000</el>
			<el>0.000000</el>
			<el>0.000000</el>
			<el>0.000000</el>
			<el>0.000000</el>
			<el>0.000000</el>
			<el>0.000000</el>
			<el>0.000000</el>
			<el>0.000000</el>
			<el>0.000000</el>
			<el>0.000000</el>
			<el>0.000000</el>
			<el>0.000000</el>
			<el>0.000000</el>
			<el>0.000000</el>
			<el>0.000000</el>
			<el>0.000000</el>
			<el>0.000000</el>
			<el>0.000000</el>
			<el>0.000000</el>
			<el>0.000000</el>
			<el>0.000000</el>
			<el>0.000000</el>
			<el>0.000000</el>
			<el>0.000000</el>
			<el>0.000000</el>
			<el>0.000000</el>
			<el>0.000000</el>
			<el>0.000000</el>
			<el>0.000000</el>
			<el>0.000000</el>
			<el>0.000000</el>
			<el>0.000000</el>
			<el>0.000000</el>
			<el>0.000000</el>
			<el>0.000000</el>
			<el>0.000000</el>
			<el>0.000000</el>
			<el>0.000000</el>
			<el>0.000000</el>
			<el>0.000000</el>
			<el>0.000000</el>
			<el>0.000000</el>
			<el>0.000000</el>
			<el>0.000000</el>
			<el>0.000000</el>
			<el>0.000000</el>
			<el>0.000000</el>
			<el>0.000000</el>
			<el>0.000000</el>
			<el>0.000000</el>
			<el>0.000000</el>
			<el>0.000000</el>
			<el>0.000000</el>
			<el>0.000000</el>
			<el>0.000000</el>
			<el>0.000000</el>
			<el>0.000000</el>
			<el>0.000000</el>
			<el>0.000000</el>
			<el>0.000000</el>
			<el>0.000000</el>
			<el>0.000000</el>
			<el>0.000000</el>
			<el>0.000000</el>
			<el>0.000000</el>
			<el>0.000000</el>
			<el>0.000000</el>
			<el>0.000000</el>
			<el>0.000000</el>
			<el>0.000000</el>
			<el>0.000000</el>
			<el>0.000000</el>
			<el>0.000000</el>
			<el>0.000000</el>
			<el>0.000000</el>
			<el>0.000000</el>
			<el>0.000000</el>
			<el>0.000000</el>
			<el>0.000000</el>
			<el>0.000000</el>
			<el>0.000000</el>
			<el>0.000000</el>
			<el>0.000000</el>
			<el>0.000000</el>
			<el>0.000000</el>
			<el>0.000000</el>
			<el>0.000000</el>
			<el>0.000000</el>
			<el>0.000000</el>
			<el>0.000000</el>
			<el>0.000000</el>
			<el>0.000000</el>
			<el>0.000000</el>
			<el>0.000000</el>
			<el>0.000000</el>
			<el>0.000000</el>
			<el>0.000000</el>
			<el>0.000000</el>
			<el>0.000000</el>
			<el>0.000000</el>
		    </FloatArray>
		</FloatMap2D>
		<FloatMap2D name="cpuTimeMap" description="cpuTimeMap">
		    <int name="width" description="width">21</int>
		    <int name="height" description="height">45</int>
		    <float name="min" description="min">0.000009</float>
		    <float name="max" description="max">0.000376</float>
		    <float name="avg" description="avg">0.000040</float>
		    <FloatArray name="values" description="values">
			<el>0.020126</el>
			<el>0.005602</el>
			<el>0.007226</el>
			<el>0.021067</el>
			<el>0.003922</el>
			<el>0.007560</el>
			<el>0.005908</el>
			<el>0.020087</el>
			<el>0.001296</el>
			<el>0.004622</el>
			<el>0.007998</el>
			<el>0.020848</el>
			<el>0.002133</el>
			<el>0.000022</el>
			<el>0.004967</el>
			<el>0.030497</el>
			<el>0.002916</el>
			<el>0.002330</el>
			<el>0.003080</el>
			<el>0.020514</el>
			<el>0.004234</el>
			<el>0.021417</el>
			<el>0.006132</el>
			<el>0.004447</el>
			<el>0.015251</el>
			<el>0.005432</el>
			<el>0.003649</el>
			<el>0.002877</el>
			<el>0.001067</el>
			<el>0.002084</el>
			<el>0.003014</el>
			<el>0.006876</el>
			<el>0.001778</el>
			<el>0.008052</el>
			<el>0.003178</el>
			<el>0.003375</el>
			<el>0.001849</el>
			<el>0.000662</el>
			<el>0.020771</el>
			<el>0.006909</el>
			<el>0.003441</el>
			<el>0.003728</el>
			<el>0.020946</el>
			<el>0.004278</el>
			<el>0.001275</el>
			<el>0.004918</el>
			<el>0.004376</el>
			<el>0.009661</el>
			<el>0.002380</el>
			<el>0.003107</el>
			<el>0.018977</el>
			<el>0.011980</el>
			<el>0.019524</el>
			<el>0.001947</el>
			<el>0.000744</el>
			<el>0.002309</el>
			<el>0.002604</el>
			<el>0.012002</el>
			<el>0.003206</el>
			<el>0.002123</el>
			<el>0.003386</el>
			<el>0.003282</el>
			<el>0.030609</el>
			<el>0.004021</el>
			<el>0.003561</el>
			<el>0.017872</el>
			<el>0.003474</el>
			<el>0.002577</el>
			<el>0.004021</el>
			<el>0.002899</el>
			<el>0.002538</el>
			<el>0.002648</el>
			<el>0.001384</el>
			<el>0.002790</el>
			<el>0.004436</el>
			<el>0.004551</el>
			<el>0.006619</el>
			<el>0.006083</el>
			<el>0.006335</el>
			<el>0.001756</el>
			<el>0.001532</el>
			<el>0.006800</el>
			<el>0.003397</el>
			<el>0.006461</el>
			<el>0.003977</el>
			<el>0.005569</el>
			<el>0.004251</el>
			<el>0.004896</el>
			<el>0.004754</el>
			<el>0.001822</el>
			<el>0.000815</el>
			<el>0.004787</el>
			<el>0.016980</el>
			<el>0.002385</el>
			<el>0.001745</el>
			<el>0.003441</el>
			<el>0.019130</el>
			<el>0.003485</el>
			<el>0.002593</el>
			<el>0.001811</el>
			<el>0.018397</el>
			<el>0.010377</el>
			<el>0.002221</el>
			<el>0.005241</el>
			<el>0.005887</el>
			<el>0.001565</el>
			<el>0.003342</el>
			<el>0.017035</el>
			<el>0.002336</el>
			<el>0.003058</el>
			<el>0.001636</el>
			<el>0.005016</el>
			<el>0.002292</el>
			<el>0.005109</el>
			<el>0.002566</el>
			<el>0.007150</el>
			<el>0.013829</el>
			<el>0.005459</el>
			<el>0.002276</el>
			<el>0.002845</el>
			<el>0.005093</el>
			<el>0.004261</el>
			<el>0.001822</el>
			<el>0.000629</el>
			<el>0.001734</el>
			<el>0.005450</el>
			<el>0.002319</el>
			<el>0.001658</el>
			<el>0.002779</el>
			<el>0.008999</el>
			<el>0.012669</el>
			<el>0.003545</el>
			<el>0.004453</el>
			<el>0.002429</el>
			<el>0.002369</el>
			<el>0.002856</el>
			<el>0.004453</el>
			<el>0.004869</el>
			<el>0.002631</el>
			<el>0.011690</el>
			<el>0.004240</el>
			<el>0.003594</el>
			<el>0.004672</el>
			<el>0.004945</el>
			<el>0.002237</el>
			<el>0.002538</el>
			<el>0.004730</el>
			<el>0.001658</el>
			<el>0.002653</el>
			<el>0.011750</el>
			<el>0.005115</el>
			<el>0.018052</el>
			<el>0.003124</el>
			<el>0.004469</el>
			<el>0.002101</el>
			<el>0.002216</el>
			<el>0.001515</el>
			<el>0.001264</el>
			<el>0.003496</el>
			<el>0.005432</el>
			<el>0.004054</el>
			<el>0.002008</el>
			<el>0.001548</el>
			<el>0.005202</el>
			<el>0.004004</el>
			<el>0.003200</el>
			<el>0.005968</el>
			<el>0.005401</el>
			<el>0.012762</el>
			<el>0.003671</el>
			<el>0.002336</el>
			<el>0.005098</el>
			<el>0.006729</el>
			<el>0.002177</el>
			<el>0.001871</el>
			<el>0.005799</el>
			<el>0.002484</el>
			<el>0.003939</el>
			<el>0.003293</el>
			<el>0.005935</el>
			<el>0.004726</el>
			<el>0.004912</el>
			<el>0.003671</el>
			<el>0.002790</el>
			<el>0.004622</el>
			<el>0.003900</el>
			<el>0.002817</el>
			<el>0.003687</el>
			<el>0.025591</el>
			<el>0.003304</el>
			<el>0.005662</el>
			<el>0.002259</el>
			<el>0.007265</el>
			<el>0.004136</el>
			<el>0.004956</el>
			<el>0.004207</el>
			<el>0.001915</el>
			<el>0.006023</el>
			<el>0.001975</el>
			<el>0.003507</el>
			<el>0.005706</el>
			<el>0.000301</el>
			<el>0.004086</el>
			<el>0.005459</el>
			<el>0.003419</el>
			<el>0.004185</el>
			<el>0.003452</el>
			<el>0.009010</el>
			<el>0.004338</el>
			<el>0.009262</el>
			<el>0.004283</el>
			<el>0.003414</el>
			<el>0.003742</el>
			<el>0.004086</el>
			<el>0.003561</el>
			<el>0.004349</el>
			<el>0.002839</el>
			<el>0.062942</el>
			<el>0.001794</el>
			<el>0.004901</el>
			<el>0.003796</el>
			<el>0.001926</el>
			<el>0.003703</el>
			<el>0.003036</el>
			<el>0.003419</el>
			<el>0.003315</el>
			<el>0.002385</el>
			<el>0.004491</el>
			<el>0.005000</el>
			<el>0.003993</el>
			<el>0.009729</el>
			<el>0.004737</el>
			<el>0.005755</el>
			<el>0.005148</el>
			<el>0.002298</el>
			<el>0.002894</el>
			<el>0.002325</el>
			<el>0.002834</el>
			<el>0.003173</el>
			<el>0.004513</el>
			<el>0.004994</el>
			<el>0.001597</el>
			<el>0.003654</el>
			<el>0.003288</el>
			<el>0.004349</el>
			<el>0.005339</el>
			<el>0.003747</el>
			<el>0.002834</el>
			<el>0.003900</el>
			<el>0.002040</el>
			<el>0.003468</el>
			<el>0.007171</el>
			<el>0.003260</el>
			<el>0.003468</el>
			<el>0.002839</el>
			<el>0.003031</el>
			<el>0.003452</el>
			<el>0.004535</el>
			<el>0.003660</el>
			<el>0.001548</el>
			<el>0.002965</el>
			<el>0.004923</el>
			<el>0.004694</el>
			<el>0.002084</el>
			<el>0.002877</el>
			<el>0.005388</el>
			<el>0.002954</el>
			<el>0.006652</el>
			<el>0.007122</el>
			<el>0.005366</el>
			<el>0.003977</el>
			<el>0.001422</el>
			<el>0.006733</el>
			<el>0.005503</el>
			<el>0.003572</el>
			<el>0.003523</el>
			<el>0.002916</el>
			<el>0.003386</el>
			<el>0.001406</el>
			<el>0.008233</el>
			<el>0.009365</el>
			<el>0.004863</el>
			<el>0.003818</el>
			<el>0.004196</el>
			<el>0.002959</el>
			<el>0.003238</el>
			<el>0.006811</el>
			<el>0.004065</el>
			<el>0.001668</el>
			<el>0.003638</el>
			<el>0.003217</el>
			<el>0.008282</el>
			<el>0.002533</el>
			<el>0.005401</el>
			<el>0.002828</el>
			<el>0.001679</el>
			<el>0.003879</el>
			<el>0.003523</el>
			<el>0.001860</el>
			<el>0.002587</el>
			<el>0.007418</el>
			<el>0.123429</el>
			<el>0.336807</el>
			<el>0.404574</el>
			<el>0.477270</el>
			<el>0.405028</el>
			<el>0.455996</el>
			<el>0.410811</el>
			<el>0.065065</el>
			<el>0.007938</el>
			<el>0.002620</el>
			<el>0.002358</el>
			<el>0.003851</el>
			<el>0.011450</el>
			<el>0.007336</el>
			<el>0.003102</el>
			<el>0.005481</el>
			<el>0.012090</el>
			<el>0.006499</el>
			<el>0.002549</el>
			<el>0.004404</el>
			<el>0.152542</el>
			<el>0.805363</el>
			<el>0.681754</el>
			<el>0.779412</el>
			<el>0.798109</el>
			<el>0.742990</el>
			<el>0.754620</el>
			<el>0.794050</el>
			<el>0.393841</el>
			<el>0.005990</el>
			<el>0.002899</el>
			<el>0.014469</el>
			<el>0.002177</el>
			<el>0.005443</el>
			<el>0.008776</el>
			<el>0.004130</el>
			<el>0.003069</el>
			<el>0.003096</el>
			<el>0.004196</el>
			<el>0.007494</el>
			<el>0.006121</el>
			<el>0.337425</el>
			<el>0.669719</el>
			<el>0.720326</el>
			<el>0.753668</el>
			<el>0.766463</el>
			<el>0.745364</el>
			<el>0.733433</el>
			<el>0.656694</el>
			<el>0.321474</el>
			<el>0.003151</el>
			<el>0.005328</el>
			<el>0.005263</el>
			<el>0.006220</el>
			<el>0.002423</el>
			<el>0.005810</el>
			<el>0.003080</el>
			<el>0.003671</el>
			<el>0.008534</el>
			<el>0.008906</el>
			<el>0.008517</el>
			<el>0.009480</el>
			<el>0.561416</el>
			<el>0.635360</el>
			<el>0.727574</el>
			<el>0.708428</el>
			<el>0.752815</el>
			<el>0.716672</el>
			<el>0.668718</el>
			<el>0.677345</el>
			<el>0.195036</el>
			<el>0.006214</el>
			<el>0.003025</el>
			<el>0.006105</el>
			<el>0.004579</el>
			<el>0.002495</el>
			<el>0.006160</el>
			<el>0.003189</el>
			<el>0.004054</el>
			<el>0.008835</el>
			<el>0.008047</el>
			<el>0.012352</el>
			<el>0.009393</el>
			<el>0.667405</el>
			<el>0.442183</el>
			<el>0.453540</el>
			<el>0.482456</el>
			<el>0.434115</el>
			<el>0.548528</el>
			<el>0.563796</el>
			<el>0.761354</el>
			<el>0.054638</el>
			<el>0.004261</el>
			<el>0.005914</el>
			<el>0.005306</el>
			<el>0.003868</el>
			<el>0.005514</el>
			<el>0.007930</el>
			<el>0.002106</el>
			<el>0.006236</el>
			<el>0.008851</el>
			<el>0.007746</el>
			<el>0.008862</el>
			<el>0.009704</el>
			<el>0.586164</el>
			<el>0.014026</el>
			<el>0.004519</el>
			<el>0.007177</el>
			<el>0.005170</el>
			<el>0.008692</el>
			<el>0.012834</el>
			<el>0.537746</el>
			<el>0.007768</el>
			<el>0.004869</el>
			<el>0.005886</el>
			<el>0.004584</el>
			<el>0.004043</el>
			<el>0.006264</el>
			<el>0.005119</el>
			<el>0.006887</el>
			<el>0.005115</el>
			<el>0.011411</el>
			<el>0.007577</el>
			<el>0.011121</el>
			<el>0.081323</el>
			<el>0.748291</el>
			<el>0.011493</el>
			<el>0.006767</el>
			<el>0.005591</el>
			<el>0.009190</el>
			<el>0.007555</el>
			<el>0.087094</el>
			<el>0.520525</el>
			<el>0.009431</el>
			<el>0.005531</el>
			<el>0.005602</el>
			<el>0.004376</el>
			<el>0.013747</el>
			<el>0.005257</el>
			<el>0.009019</el>
			<el>0.004590</el>
			<el>0.004431</el>
			<el>0.009245</el>
			<el>0.010711</el>
			<el>0.012122</el>
			<el>0.274406</el>
			<el>1.000000</el>
			<el>0.072953</el>
			<el>0.010459</el>
			<el>0.012899</el>
			<el>0.006947</el>
			<el>0.009333</el>
			<el>0.307174</el>
			<el>0.383005</el>
			<el>0.003982</el>
			<el>0.006471</el>
			<el>0.003430</el>
			<el>0.005197</el>
			<el>0.007555</el>
			<el>0.001149</el>
			<el>0.007239</el>
			<el>0.003178</el>
			<el>0.003058</el>
			<el>0.021986</el>
			<el>0.009436</el>
			<el>0.009918</el>
			<el>0.562527</el>
			<el>0.871188</el>
			<el>0.791184</el>
			<el>0.762771</el>
			<el>0.655737</el>
			<el>0.584654</el>
			<el>0.574310</el>
			<el>0.642663</el>
			<el>0.374783</el>
			<el>0.004010</el>
			<el>0.006597</el>
			<el>0.005120</el>
			<el>0.006411</el>
			<el>0.005738</el>
			<el>0.004622</el>
			<el>0.005887</el>
			<el>0.004300</el>
			<el>0.006023</el>
			<el>0.016564</el>
			<el>0.027970</el>
			<el>0.399558</el>
			<el>0.784636</el>
			<el>0.742186</el>
			<el>0.638954</el>
			<el>0.667761</el>
			<el>0.648439</el>
			<el>0.606252</el>
			<el>0.647531</el>
			<el>0.653308</el>
			<el>0.555328</el>
			<el>0.009628</el>
			<el>0.007719</el>
			<el>0.007598</el>
			<el>0.008403</el>
			<el>0.009054</el>
			<el>0.006789</el>
			<el>0.005625</el>
			<el>0.002314</el>
			<el>0.004141</el>
			<el>0.008534</el>
			<el>0.350396</el>
			<el>0.644189</el>
			<el>0.612264</el>
			<el>0.772716</el>
			<el>0.702432</el>
			<el>0.836194</el>
			<el>0.782032</el>
			<el>0.819367</el>
			<el>0.578063</el>
			<el>0.824291</el>
			<el>0.410646</el>
			<el>0.005366</el>
			<el>0.006893</el>
			<el>0.008151</el>
			<el>0.004524</el>
			<el>0.008052</el>
			<el>0.005159</el>
			<el>0.006996</el>
			<el>0.003031</el>
			<el>0.005290</el>
			<el>0.009147</el>
			<el>0.133292</el>
			<el>0.408163</el>
			<el>0.579840</el>
			<el>0.365472</el>
			<el>0.566586</el>
			<el>0.507467</el>
			<el>0.444782</el>
			<el>0.501225</el>
			<el>0.615453</el>
			<el>0.875423</el>
			<el>0.504655</el>
			<el>0.007341</el>
			<el>0.004311</el>
			<el>0.006050</el>
			<el>0.005109</el>
			<el>0.004360</el>
			<el>0.008463</el>
			<el>0.006481</el>
			<el>0.002527</el>
			<el>0.005662</el>
			<el>0.005180</el>
			<el>0.008113</el>
			<el>0.397567</el>
			<el>0.352201</el>
			<el>0.010941</el>
			<el>0.848317</el>
			<el>0.624659</el>
			<el>0.729729</el>
			<el>0.609944</el>
			<el>0.084217</el>
			<el>0.577466</el>
			<el>0.400559</el>
			<el>0.006586</el>
			<el>0.006165</el>
			<el>0.005432</el>
			<el>0.005016</el>
			<el>0.007062</el>
			<el>0.006767</el>
			<el>0.006130</el>
			<el>0.004726</el>
			<el>0.002888</el>
			<el>0.002084</el>
			<el>0.009956</el>
			<el>0.661896</el>
			<el>0.065240</el>
			<el>0.016433</el>
			<el>0.654079</el>
			<el>0.012183</el>
			<el>0.047899</el>
			<el>0.282666</el>
			<el>0.726360</el>
			<el>0.796682</el>
			<el>0.465000</el>
			<el>0.005903</el>
			<el>0.009776</el>
			<el>0.007106</el>
			<el>0.022850</el>
			<el>0.004672</el>
			<el>0.003775</el>
			<el>0.008999</el>
			<el>0.003074</el>
			<el>0.003299</el>
			<el>0.002938</el>
			<el>0.006964</el>
			<el>0.826014</el>
			<el>0.288782</el>
			<el>0.044628</el>
			<el>0.354876</el>
			<el>0.010826</el>
			<el>0.009322</el>
			<el>0.012872</el>
			<el>0.344876</el>
			<el>0.322343</el>
			<el>0.462818</el>
			<el>0.012877</el>
			<el>0.007407</el>
			<el>0.005547</el>
			<el>0.006006</el>
			<el>0.005388</el>
			<el>0.004666</el>
			<el>0.007580</el>
			<el>0.002363</el>
			<el>0.003671</el>
			<el>0.004606</el>
			<el>0.045005</el>
			<el>0.625053</el>
			<el>0.376178</el>
			<el>0.520317</el>
			<el>0.540235</el>
			<el>0.667454</el>
			<el>0.206967</el>
			<el>0.009508</el>
			<el>0.465487</el>
			<el>0.203614</el>
			<el>0.531953</el>
			<el>0.004551</el>
			<el>0.006072</el>
			<el>0.004644</el>
			<el>0.003539</el>
			<el>0.002418</el>
			<el>0.003857</el>
			<el>0.008756</el>
			<el>0.005268</el>
			<el>0.006132</el>
			<el>0.005449</el>
			<el>0.274062</el>
			<el>0.414350</el>
			<el>0.009912</el>
			<el>0.004650</el>
			<el>0.008140</el>
			<el>0.151114</el>
			<el>0.425996</el>
			<el>0.574047</el>
			<el>0.864717</el>
			<el>0.046061</el>
			<el>0.005520</el>
			<el>0.003331</el>
			<el>0.003955</el>
			<el>0.004125</el>
			<el>0.004371</el>
			<el>0.005635</el>
			<el>0.004863</el>
			<el>0.006510</el>
			<el>0.002987</el>
			<el>0.001953</el>
			<el>0.003818</el>
			<el>0.496111</el>
			<el>0.374646</el>
			<el>0.004147</el>
			<el>0.005159</el>
			<el>0.007336</el>
			<el>0.003052</el>
			<el>0.003424</el>
			<el>0.008320</el>
			<el>0.572565</el>
			<el>0.009294</el>
			<el>0.005273</el>
			<el>0.004956</el>
			<el>0.000252</el>
			<el>0.003643</el>
			<el>0.004529</el>
			<el>0.003523</el>
			<el>0.002724</el>
			<el>0.006928</el>
			<el>0.004300</el>
			<el>0.002724</el>
			<el>0.001346</el>
			<el>0.278700</el>
			<el>0.100398</el>
			<el>0.004973</el>
			<el>0.002631</el>
			<el>0.003255</el>
			<el>0.004360</el>
			<el>0.001302</el>
			<el>0.005914</el>
			<el>0.599446</el>
			<el>0.004032</el>
			<el>0.006236</el>
			<el>0.004699</el>
			<el>0.004464</el>
			<el>0.004754</el>
			<el>0.003665</el>
			<el>0.003370</el>
			<el>0.001023</el>
			<el>0.017295</el>
			<el>0.002298</el>
			<el>0.002522</el>
			<el>0.001400</el>
			<el>0.002188</el>
			<el>0.005295</el>
			<el>0.004672</el>
			<el>0.002954</el>
			<el>0.004546</el>
			<el>0.003293</el>
			<el>0.005186</el>
			<el>0.201190</el>
			<el>0.570262</el>
			<el>0.002226</el>
			<el>0.006061</el>
			<el>0.002440</el>
			<el>0.005914</el>
			<el>0.002970</el>
			<el>0.013299</el>
			<el>0.012855</el>
			<el>0.007927</el>
			<el>0.006413</el>
			<el>0.006346</el>
			<el>0.002139</el>
			<el>0.003260</el>
			<el>0.001800</el>
			<el>0.004584</el>
			<el>0.008337</el>
			<el>0.012297</el>
			<el>0.004863</el>
			<el>0.003052</el>
			<el>0.004004</el>
			<el>0.336539</el>
			<el>0.424842</el>
			<el>0.004436</el>
			<el>0.002495</el>
			<el>0.003337</el>
			<el>0.002019</el>
			<el>0.002648</el>
			<el>0.004666</el>
			<el>0.003731</el>
			<el>0.003397</el>
			<el>0.007862</el>
			<el>0.001296</el>
			<el>0.008156</el>
			<el>0.004420</el>
			<el>0.003211</el>
			<el>0.004540</el>
			<el>0.001411</el>
			<el>0.001756</el>
			<el>0.002144</el>
			<el>0.002484</el>
			<el>0.001975</el>
			<el>0.003539</el>
			<el>0.002079</el>
			<el>0.002615</el>
			<el>0.006554</el>
			<el>0.002144</el>
			<el>0.006258</el>
			<el>0.002478</el>
			<el>0.004874</el>
			<el>0.005077</el>
			<el>0.003857</el>
			<el>0.007152</el>
			<el>0.005673</el>
			<el>0.004612</el>
			<el>0.003868</el>
			<el>0.004874</el>
			<el>0.001318</el>
			<el>0.003720</el>
			<el>0.004699</el>
			<el>0.004207</el>
			<el>0.003862</el>
			<el>0.002265</el>
			<el>0.008517</el>
			<el>0.007013</el>
			<el>0.004519</el>
			<el>0.005952</el>
			<el>0.009546</el>
			<el>0.002686</el>
			<el>0.008955</el>
			<el>0.003578</el>
			<el>0.005842</el>
			<el>0.003424</el>
			<el>0.023889</el>
			<el>0.004070</el>
			<el>0.003873</el>
			<el>0.006105</el>
			<el>0.006493</el>
			<el>0.004004</el>
			<el>0.003632</el>
			<el>0.005919</el>
			<el>0.003731</el>
			<el>0.003676</el>
			<el>0.002675</el>
			<el>0.002473</el>
			<el>0.005520</el>
			<el>0.002522</el>
			<el>0.005771</el>
			<el>0.007341</el>
			<el>0.004513</el>
			<el>0.018036</el>
			<el>0.002522</el>
			<el>0.005071</el>
			<el>0.003485</el>
			<el>0.006247</el>
			<el>0.002533</el>
			<el>0.001105</el>
			<el>0.002642</el>
			<el>0.004059</el>
			<el>0.014453</el>
			<el>0.004075</el>
			<el>0.003802</el>
			<el>0.003660</el>
			<el>0.003293</el>
			<el>0.003003</el>
			<el>0.001937</el>
			<el>0.001466</el>
			<el>0.003392</el>
			<el>0.003621</el>
			<el>0.009776</el>
			<el>0.002691</el>
			<el>0.003687</el>
			<el>0.005416</el>
			<el>0.003687</el>
			<el>0.002473</el>
			<el>0.006130</el>
			<el>0.019278</el>
			<el>0.001318</el>
			<el>0.015328</el>
			<el>0.002505</el>
			<el>0.002407</el>
			<el>0.002680</el>
			<el>0.002746</el>
			<el>0.003446</el>
			<el>0.004289</el>
			<el>0.003408</el>
			<el>0.001778</el>
			<el>0.006898</el>
			<el>0.003643</el>
			<el>0.004125</el>
			<el>0.004513</el>
			<el>0.003424</el>
			<el>0.003501</el>
			<el>0.002068</el>
			<el>0.004108</el>
			<el>0.001674</el>
			<el>0.005693</el>
			<el>0.019923</el>
			<el>0.005892</el>
			<el>0.003414</el>
			<el>0.003561</el>
			<el>0.002412</el>
			<el>0.001357</el>
			<el>0.017533</el>
			<el>0.016280</el>
			<el>0.018687</el>
			<el>0.002697</el>
			<el>0.002845</el>
			<el>0.018156</el>
			<el>0.002505</el>
			<el>0.002347</el>
			<el>0.001778</el>
			<el>0.001039</el>
			<el>0.014480</el>
			<el>0.002735</el>
			<el>0.003063</el>
			<el>0.018233</el>
			<el>0.003232</el>
			<el>0.001329</el>
			<el>0.001931</el>
			<el>0.020498</el>
			<el>0.003769</el>
			<el>0.005252</el>
			<el>0.002336</el>
			<el>0.001253</el>
			<el>0.000673</el>
			<el>0.002445</el>
			<el>0.002079</el>
			<el>0.001980</el>
			<el>0.003528</el>
			<el>0.003353</el>
			<el>0.004393</el>
			<el>0.003802</el>
			<el>0.003824</el>
			<el>0.001964</el>
			<el>0.008124</el>
			<el>0.020290</el>
			<el>0.004759</el>
			<el>0.005216</el>
			<el>0.004010</el>
			<el>0.004223</el>
			<el>0.000848</el>
			<el>0.018129</el>
			<el>0.004573</el>
			<el>0.017423</el>
			<el>0.001554</el>
			<el>0.001127</el>
			<el>0.018742</el>
			<el>0.002298</el>
			<el>0.022040</el>
			<el>0.002030</el>
			<el>0.000000</el>
			<el>0.003020</el>
			<el>0.018867</el>
			<el>0.002473</el>
			<el>0.004010</el>
			<el>0.002445</el>
			<el>0.004272</el>
			<el>0.020044</el>
			<el>0.005323</el>
			<el>0.023813</el>
			<el>0.000629</el>
			<el>0.001559</el>
			<el>0.006006</el>
			<el>0.002101</el>
			<el>0.002965</el>
			<el>0.001942</el>
			<el>0.000777</el>
			<el>0.002555</el>
			<el>0.003031</el>
			<el>0.007620</el>
			<el>0.003288</el>
			<el>0.002062</el>
			<el>0.002254</el>
			<el>0.019141</el>
			<el>0.002899</el>
			<el>0.002374</el>
			<el>0.020344</el>
			<el>0.004278</el>
			<el>0.001422</el>
			<el>0.003339</el>
			<el>0.000282</el>
			<el>0.026338</el>
			<el>0.024884</el>
			<el>0.002504</el>
			<el>0.002322</el>
			<el>0.007479</el>
			<el>0.024601</el>
			<el>0.002268</el>
			<el>0.002329</el>
			<el>0.008839</el>
			<el>0.002389</el>
			<el>0.004880</el>
			<el>0.023423</el>
			<el>0.003904</el>
			<el>0.002659</el>
			<el>0.004093</el>
			<el>0.003345</el>
			<el>0.001285</el>
			<el>0.003433</el>
			<el>0.015956</el>
			<el>0.005853</el>
		    </FloatArray>
		</FloatMap2D>
		<timer name="checkpointTimer" description="Time writing checkpoints">
		    <elapsed>0.000000</elapsed>
		</timer>
	    </stats>
	</stats>
    </stats>
</rm:statsDoc>
</doc>
